<?xml version="1.0" encoding="UTF-8"?>
<!-- Generated by Oracle Reports version 10.1.2.3.0 -->
<GIRATEVARIANCE>
  <LIST_G_ROOM>
    <G_ROOM>
      <IS_ACCOMPANYING_YN>N</IS_ACCOMPANYING_YN>
      <SHARE_NAMES></SHARE_NAMES>
      <ACCOMPANYING_NAMES></ACCOMPANYING_NAMES>
      <BOOKED_ROOM_CATEGORY>10814</BOOKED_ROOM_CATEGORY>
      <RECORD_TYPE>RESERVATION</RECORD_TYPE>
      <COMMISIONABLE_YN>N</COMMISIONABLE_YN>
      <ALLOTMENT_HEADER_ID></ALLOTMENT_HEADER_ID>
      <CHAR_ARRIVAL>26-04-22</CHAR_ARRIVAL>
      <CHAR_DEPARTURE>29-04-22</CHAR_DEPARTURE>
      <BEGIN_DATE>26-APR-22</BEGIN_DATE>
      <END_DATE>29-APR-22</END_DATE>
      <BOOKED_ROOM_CATEGORY_LABEL>0QN</BOOKED_ROOM_CATEGORY_LABEL>
      <IS_SHARED_YN>N</IS_SHARED_YN>
      <NAME_ID>18850963</NAME_ID>
      <RESORT3>22974</RESORT3>
      <ROOM_STATUS>DI</ROOM_STATUS>
      <TRAVEL_AGENT_ID></TRAVEL_AGENT_ID>
      <SOURCE_ID></SOURCE_ID>
      <RESV_NAME_ID>24080650</RESV_NAME_ID>
      <RM_ADULTS>2</RM_ADULTS>
      <RM_CHILDREN>0</RM_CHILDREN>
      <FULL_NAME>Hernandez,Carmen,Ms.</FULL_NAME>
      <FULL_NAME_NO_SHR_IND>Hernandez,Carmen,Ms.</FULL_NAME_NO_SHR_IND>
      <COMPANY_NAME>C- Mini Vacaciones</COMPANY_NAME>
      <GROUP_NAME></GROUP_NAME>
      <MARKET_CODE>PKG</MARKET_CODE>
      <VIP></VIP>
      <RATE_CODE>CNT.03B</RATE_CODE>
      <ROOM_CATEGORY_LABEL>0QN</ROOM_CATEGORY_LABEL>
      <ROOM>0603</ROOM>
      <NIGHTS>3</NIGHTS>
      <DISCOUNT_REASON_CODE></DISCOUNT_REASON_CODE>
      <BLOCK_CODE></BLOCK_CODE>
      <ORIGIN_OF_BOOKING>NON</ORIGIN_OF_BOOKING>
      <ROOM_NO>                0603</ROOM_NO>
      <CH></CH>
      <PAYMENT_METHOD>CA</PAYMENT_METHOD>
      <CREDIT_CARD_NO></CREDIT_CARD_NO>
      <CREDIT_CARD_EXP_DATE></CREDIT_CARD_EXP_DATE>
      <SOURCE_COMM>N</SOURCE_COMM>
      <PRODUCTS></PRODUCTS>
      <RM_DISC_AMT></RM_DISC_AMT>
      <RM_DIS_PERCENT></RM_DIS_PERCENT>
      <RM_GROSS_RATE>190.49</RM_GROSS_RATE>
      <RM_NET_ROOM_REVENUE>136.89</RM_NET_ROOM_REVENUE>
      <RM_POT_GROSS_RATE>0</RM_POT_GROSS_RATE>
      <RM_POT_NET_ROOM_REVENUE>0</RM_POT_NET_ROOM_REVENUE>
      <DISCOUNT_REASON_DESC></DISCOUNT_REASON_DESC>
      <PRIMARY_01>1</PRIMARY_01>
      <CHANNEL>MAIL</CHANNEL>
      <LIST_G_RESERVATION_NOTES>
      </LIST_G_RESERVATION_NOTES>
      <LIST_G_PROFILE_NOTES>
      </LIST_G_PROFILE_NOTES>
      <LIST_G_ROUTING_INSTRUCTIONS>
      </LIST_G_ROUTING_INSTRUCTIONS>
      <COMM_YN>N</COMM_YN>
      <RM_NET_VARIANCE>-136.89</RM_NET_VARIANCE>
      <COUNT_COMMENTS>0</COUNT_COMMENTS>
      <COUNT_RES_COMMENTS>0</COUNT_RES_COMMENTS>
      <COUNT_ROUTING>0</COUNT_ROUTING>
    </G_ROOM>
    <G_ROOM>
      <IS_ACCOMPANYING_YN>N</IS_ACCOMPANYING_YN>
      <SHARE_NAMES></SHARE_NAMES>
      <ACCOMPANYING_NAMES></ACCOMPANYING_NAMES>
      <BOOKED_ROOM_CATEGORY>10814</BOOKED_ROOM_CATEGORY>
      <RECORD_TYPE>RESERVATION</RECORD_TYPE>
      <COMMISIONABLE_YN>N</COMMISIONABLE_YN>
      <ALLOTMENT_HEADER_ID></ALLOTMENT_HEADER_ID>
      <CHAR_ARRIVAL>03-11-21</CHAR_ARRIVAL>
      <CHAR_DEPARTURE>31-05-22</CHAR_DEPARTURE>
      <BEGIN_DATE>03-NOV-21</BEGIN_DATE>
      <END_DATE>31-MAY-22</END_DATE>
      <BOOKED_ROOM_CATEGORY_LABEL>0QN</BOOKED_ROOM_CATEGORY_LABEL>
      <IS_SHARED_YN>N</IS_SHARED_YN>
      <NAME_ID>5278713</NAME_ID>
      <RESORT3>22974</RESORT3>
      <ROOM_STATUS>DI</ROOM_STATUS>
      <TRAVEL_AGENT_ID></TRAVEL_AGENT_ID>
      <SOURCE_ID>17009214</SOURCE_ID>
      <RESV_NAME_ID>23222400</RESV_NAME_ID>
      <RM_ADULTS>1</RM_ADULTS>
      <RM_CHILDREN>0</RM_CHILDREN>
      <FULL_NAME>Diaz,Johan,Mr.</FULL_NAME>
      <FULL_NAME_NO_SHR_IND>Diaz,Johan,Mr.</FULL_NAME_NO_SHR_IND>
      <COMPANY_NAME>C- Wyndham Concorde
S- Seguridad</COMPANY_NAME>
      <GROUP_NAME></GROUP_NAME>
      <MARKET_CODE>HSU</MARKET_CODE>
      <VIP></VIP>
      <RATE_CODE>HSU</RATE_CODE>
      <ROOM_CATEGORY_LABEL>0QN</ROOM_CATEGORY_LABEL>
      <ROOM>0620</ROOM>
      <NIGHTS>209</NIGHTS>
      <DISCOUNT_REASON_CODE></DISCOUNT_REASON_CODE>
      <BLOCK_CODE></BLOCK_CODE>
      <ORIGIN_OF_BOOKING>AMIG</ORIGIN_OF_BOOKING>
      <ROOM_NO>                0620</ROOM_NO>
      <CH>H</CH>
      <PAYMENT_METHOD>CA</PAYMENT_METHOD>
      <CREDIT_CARD_NO></CREDIT_CARD_NO>
      <CREDIT_CARD_EXP_DATE></CREDIT_CARD_EXP_DATE>
      <SOURCE_COMM>N</SOURCE_COMM>
      <PRODUCTS></PRODUCTS>
      <RM_DISC_AMT></RM_DISC_AMT>
      <RM_DIS_PERCENT></RM_DIS_PERCENT>
      <RM_GROSS_RATE>0</RM_GROSS_RATE>
      <RM_NET_ROOM_REVENUE>0</RM_NET_ROOM_REVENUE>
      <RM_POT_GROSS_RATE>0</RM_POT_GROSS_RATE>
      <RM_POT_NET_ROOM_REVENUE>0</RM_POT_NET_ROOM_REVENUE>
      <DISCOUNT_REASON_DESC></DISCOUNT_REASON_DESC>
      <PRIMARY_01>1</PRIMARY_01>
      <CHANNEL>IN</CHANNEL>
      <LIST_G_RESERVATION_NOTES>
      </LIST_G_RESERVATION_NOTES>
      <LIST_G_PROFILE_NOTES>
      </LIST_G_PROFILE_NOTES>
      <LIST_G_ROUTING_INSTRUCTIONS>
      </LIST_G_ROUTING_INSTRUCTIONS>
      <COMM_YN>N</COMM_YN>
      <RM_NET_VARIANCE>0</RM_NET_VARIANCE>
      <COUNT_COMMENTS>0</COUNT_COMMENTS>
      <COUNT_RES_COMMENTS>0</COUNT_RES_COMMENTS>
      <COUNT_ROUTING>0</COUNT_ROUTING>
    </G_ROOM>
    <G_ROOM>
      <IS_ACCOMPANYING_YN>N</IS_ACCOMPANYING_YN>
      <SHARE_NAMES></SHARE_NAMES>
      <ACCOMPANYING_NAMES></ACCOMPANYING_NAMES>
      <BOOKED_ROOM_CATEGORY>10814</BOOKED_ROOM_CATEGORY>
      <RECORD_TYPE>RESERVATION</RECORD_TYPE>
      <COMMISIONABLE_YN>N</COMMISIONABLE_YN>
      <ALLOTMENT_HEADER_ID></ALLOTMENT_HEADER_ID>
      <CHAR_ARRIVAL>10-04-22</CHAR_ARRIVAL>
      <CHAR_DEPARTURE>22-05-22</CHAR_DEPARTURE>
      <BEGIN_DATE>10-APR-22</BEGIN_DATE>
      <END_DATE>22-MAY-22</END_DATE>
      <BOOKED_ROOM_CATEGORY_LABEL>0QN</BOOKED_ROOM_CATEGORY_LABEL>
      <IS_SHARED_YN>N</IS_SHARED_YN>
      <NAME_ID>7897213</NAME_ID>
      <RESORT3>22974</RESORT3>
      <ROOM_STATUS>DI</ROOM_STATUS>
      <TRAVEL_AGENT_ID></TRAVEL_AGENT_ID>
      <SOURCE_ID></SOURCE_ID>
      <RESV_NAME_ID>24043402</RESV_NAME_ID>
      <RM_ADULTS>1</RM_ADULTS>
      <RM_CHILDREN>0</RM_CHILDREN>
      <FULL_NAME>Oropeza,Jesus,Mr.</FULL_NAME>
      <FULL_NAME_NO_SHR_IND>Oropeza,Jesus,Mr.</FULL_NAME_NO_SHR_IND>
      <COMPANY_NAME>C- Servicios Turistic</COMPANY_NAME>
      <GROUP_NAME></GROUP_NAME>
      <MARKET_CODE>HSU</MARKET_CODE>
      <VIP></VIP>
      <RATE_CODE>HSU</RATE_CODE>
      <ROOM_CATEGORY_LABEL>8HKN</ROOM_CATEGORY_LABEL>
      <ROOM>0902</ROOM>
      <NIGHTS>42</NIGHTS>
      <DISCOUNT_REASON_CODE></DISCOUNT_REASON_CODE>
      <BLOCK_CODE></BLOCK_CODE>
      <ORIGIN_OF_BOOKING>SALES</ORIGIN_OF_BOOKING>
      <ROOM_NO>                0902</ROOM_NO>
      <CH>H</CH>
      <PAYMENT_METHOD>CA</PAYMENT_METHOD>
      <CREDIT_CARD_NO></CREDIT_CARD_NO>
      <CREDIT_CARD_EXP_DATE></CREDIT_CARD_EXP_DATE>
      <SOURCE_COMM>N</SOURCE_COMM>
      <PRODUCTS></PRODUCTS>
      <RM_DISC_AMT></RM_DISC_AMT>
      <RM_DIS_PERCENT></RM_DIS_PERCENT>
      <RM_GROSS_RATE>0</RM_GROSS_RATE>
      <RM_NET_ROOM_REVENUE>0</RM_NET_ROOM_REVENUE>
      <RM_POT_GROSS_RATE>0</RM_POT_GROSS_RATE>
      <RM_POT_NET_ROOM_REVENUE>0</RM_POT_NET_ROOM_REVENUE>
      <DISCOUNT_REASON_DESC></DISCOUNT_REASON_DESC>
      <PRIMARY_01>1</PRIMARY_01>
      <CHANNEL>IN</CHANNEL>
      <LIST_G_RESERVATION_NOTES>
      </LIST_G_RESERVATION_NOTES>
      <LIST_G_PROFILE_NOTES>
      </LIST_G_PROFILE_NOTES>
      <LIST_G_ROUTING_INSTRUCTIONS>
      </LIST_G_ROUTING_INSTRUCTIONS>
      <COMM_YN>N</COMM_YN>
      <RM_NET_VARIANCE>0</RM_NET_VARIANCE>
      <COUNT_COMMENTS>0</COUNT_COMMENTS>
      <COUNT_RES_COMMENTS>0</COUNT_RES_COMMENTS>
      <COUNT_ROUTING>0</COUNT_ROUTING>
    </G_ROOM>
    <G_ROOM>
      <IS_ACCOMPANYING_YN>N</IS_ACCOMPANYING_YN>
      <SHARE_NAMES></SHARE_NAMES>
      <ACCOMPANYING_NAMES></ACCOMPANYING_NAMES>
      <BOOKED_ROOM_CATEGORY>10815</BOOKED_ROOM_CATEGORY>
      <RECORD_TYPE>RESERVATION</RECORD_TYPE>
      <COMMISIONABLE_YN>N</COMMISIONABLE_YN>
      <ALLOTMENT_HEADER_ID></ALLOTMENT_HEADER_ID>
      <CHAR_ARRIVAL>27-04-22</CHAR_ARRIVAL>
      <CHAR_DEPARTURE>01-05-22</CHAR_DEPARTURE>
      <BEGIN_DATE>27-APR-22</BEGIN_DATE>
      <END_DATE>01-MAY-22</END_DATE>
      <BOOKED_ROOM_CATEGORY_LABEL>3KN</BOOKED_ROOM_CATEGORY_LABEL>
      <IS_SHARED_YN>N</IS_SHARED_YN>
      <NAME_ID>19043213</NAME_ID>
      <RESORT3>22974</RESORT3>
      <ROOM_STATUS>DI</ROOM_STATUS>
      <TRAVEL_AGENT_ID></TRAVEL_AGENT_ID>
      <SOURCE_ID>18720713</SOURCE_ID>
      <RESV_NAME_ID>24339900</RESV_NAME_ID>
      <RM_ADULTS>2</RM_ADULTS>
      <RM_CHILDREN>0</RM_CHILDREN>
      <FULL_NAME>Basil,Al Abdala,Mr.</FULL_NAME>
      <FULL_NAME_NO_SHR_IND>Basil,Al Abdala,Mr.</FULL_NAME_NO_SHR_IND>
      <COMPANY_NAME>C- Particular
S- Promo Ventas 2022</COMPANY_NAME>
      <GROUP_NAME></GROUP_NAME>
      <MARKET_CODE>COM</MARKET_CODE>
      <VIP></VIP>
      <RATE_CODE>COMRACK$</RATE_CODE>
      <ROOM_CATEGORY_LABEL>3KN</ROOM_CATEGORY_LABEL>
      <ROOM>0916</ROOM>
      <NIGHTS>4</NIGHTS>
      <DISCOUNT_REASON_CODE></DISCOUNT_REASON_CODE>
      <BLOCK_CODE></BLOCK_CODE>
      <ORIGIN_OF_BOOKING>WLK</ORIGIN_OF_BOOKING>
      <ROOM_NO>                0916</ROOM_NO>
      <CH></CH>
      <PAYMENT_METHOD>CA</PAYMENT_METHOD>
      <CREDIT_CARD_NO></CREDIT_CARD_NO>
      <CREDIT_CARD_EXP_DATE></CREDIT_CARD_EXP_DATE>
      <SOURCE_COMM>N</SOURCE_COMM>
      <PRODUCTS></PRODUCTS>
      <RM_DISC_AMT></RM_DISC_AMT>
      <RM_DIS_PERCENT></RM_DIS_PERCENT>
      <RM_GROSS_RATE>799.2</RM_GROSS_RATE>
      <RM_NET_ROOM_REVENUE>745.48</RM_NET_ROOM_REVENUE>
      <RM_POT_GROSS_RATE>0</RM_POT_GROSS_RATE>
      <RM_POT_NET_ROOM_REVENUE>0</RM_POT_NET_ROOM_REVENUE>
      <DISCOUNT_REASON_DESC></DISCOUNT_REASON_DESC>
      <PRIMARY_01>1</PRIMARY_01>
      <CHANNEL>IN</CHANNEL>
      <LIST_G_RESERVATION_NOTES>
      </LIST_G_RESERVATION_NOTES>
      <LIST_G_PROFILE_NOTES>
      </LIST_G_PROFILE_NOTES>
      <LIST_G_ROUTING_INSTRUCTIONS>
      </LIST_G_ROUTING_INSTRUCTIONS>
      <COMM_YN>N</COMM_YN>
      <RM_NET_VARIANCE>-745.48</RM_NET_VARIANCE>
      <COUNT_COMMENTS>0</COUNT_COMMENTS>
      <COUNT_RES_COMMENTS>0</COUNT_RES_COMMENTS>
      <COUNT_ROUTING>0</COUNT_ROUTING>
    </G_ROOM>
    <G_ROOM>
      <IS_ACCOMPANYING_YN>N</IS_ACCOMPANYING_YN>
      <SHARE_NAMES></SHARE_NAMES>
      <ACCOMPANYING_NAMES></ACCOMPANYING_NAMES>
      <BOOKED_ROOM_CATEGORY>10812</BOOKED_ROOM_CATEGORY>
      <RECORD_TYPE>RESERVATION</RECORD_TYPE>
      <COMMISIONABLE_YN>N</COMMISIONABLE_YN>
      <ALLOTMENT_HEADER_ID></ALLOTMENT_HEADER_ID>
      <CHAR_ARRIVAL>27-04-22</CHAR_ARRIVAL>
      <CHAR_DEPARTURE>01-05-22</CHAR_DEPARTURE>
      <BEGIN_DATE>27-APR-22</BEGIN_DATE>
      <END_DATE>01-MAY-22</END_DATE>
      <BOOKED_ROOM_CATEGORY_LABEL>0KN</BOOKED_ROOM_CATEGORY_LABEL>
      <IS_SHARED_YN>N</IS_SHARED_YN>
      <NAME_ID>19041963</NAME_ID>
      <RESORT3>22974</RESORT3>
      <ROOM_STATUS>DI</ROOM_STATUS>
      <TRAVEL_AGENT_ID></TRAVEL_AGENT_ID>
      <SOURCE_ID>18720713</SOURCE_ID>
      <RESV_NAME_ID>24340150</RESV_NAME_ID>
      <RM_ADULTS>1</RM_ADULTS>
      <RM_CHILDREN>0</RM_CHILDREN>
      <FULL_NAME>Ortega,Erika,Mrs.</FULL_NAME>
      <FULL_NAME_NO_SHR_IND>Ortega,Erika,Mrs.</FULL_NAME_NO_SHR_IND>
      <COMPANY_NAME>C- Particular
S- Promo Ventas 2022</COMPANY_NAME>
      <GROUP_NAME></GROUP_NAME>
      <MARKET_CODE>COM</MARKET_CODE>
      <VIP></VIP>
      <RATE_CODE>COMRACK$</RATE_CODE>
      <ROOM_CATEGORY_LABEL>0KN</ROOM_CATEGORY_LABEL>
      <ROOM>0917</ROOM>
      <NIGHTS>4</NIGHTS>
      <DISCOUNT_REASON_CODE></DISCOUNT_REASON_CODE>
      <BLOCK_CODE></BLOCK_CODE>
      <ORIGIN_OF_BOOKING>WLK</ORIGIN_OF_BOOKING>
      <ROOM_NO>                0917</ROOM_NO>
      <CH></CH>
      <PAYMENT_METHOD>CA</PAYMENT_METHOD>
      <CREDIT_CARD_NO></CREDIT_CARD_NO>
      <CREDIT_CARD_EXP_DATE></CREDIT_CARD_EXP_DATE>
      <SOURCE_COMM>N</SOURCE_COMM>
      <PRODUCTS></PRODUCTS>
      <RM_DISC_AMT></RM_DISC_AMT>
      <RM_DIS_PERCENT></RM_DIS_PERCENT>
      <RM_GROSS_RATE>488.4</RM_GROSS_RATE>
      <RM_NET_ROOM_REVENUE>461.54</RM_NET_ROOM_REVENUE>
      <RM_POT_GROSS_RATE>0</RM_POT_GROSS_RATE>
      <RM_POT_NET_ROOM_REVENUE>0</RM_POT_NET_ROOM_REVENUE>
      <DISCOUNT_REASON_DESC></DISCOUNT_REASON_DESC>
      <PRIMARY_01>1</PRIMARY_01>
      <CHANNEL>IN</CHANNEL>
      <LIST_G_RESERVATION_NOTES>
      </LIST_G_RESERVATION_NOTES>
      <LIST_G_PROFILE_NOTES>
      </LIST_G_PROFILE_NOTES>
      <LIST_G_ROUTING_INSTRUCTIONS>
      </LIST_G_ROUTING_INSTRUCTIONS>
      <COMM_YN>N</COMM_YN>
      <RM_NET_VARIANCE>-461.54</RM_NET_VARIANCE>
      <COUNT_COMMENTS>0</COUNT_COMMENTS>
      <COUNT_RES_COMMENTS>0</COUNT_RES_COMMENTS>
      <COUNT_ROUTING>0</COUNT_ROUTING>
    </G_ROOM>
    <G_ROOM>
      <IS_ACCOMPANYING_YN>N</IS_ACCOMPANYING_YN>
      <SHARE_NAMES></SHARE_NAMES>
      <ACCOMPANYING_NAMES></ACCOMPANYING_NAMES>
      <BOOKED_ROOM_CATEGORY>11810</BOOKED_ROOM_CATEGORY>
      <RECORD_TYPE>RESERVATION</RECORD_TYPE>
      <COMMISIONABLE_YN>N</COMMISIONABLE_YN>
      <ALLOTMENT_HEADER_ID></ALLOTMENT_HEADER_ID>
      <CHAR_ARRIVAL>28-04-22</CHAR_ARRIVAL>
      <CHAR_DEPARTURE>01-05-22</CHAR_DEPARTURE>
      <BEGIN_DATE>28-APR-22</BEGIN_DATE>
      <END_DATE>01-MAY-22</END_DATE>
      <BOOKED_ROOM_CATEGORY_LABEL>0KP</BOOKED_ROOM_CATEGORY_LABEL>
      <IS_SHARED_YN>N</IS_SHARED_YN>
      <NAME_ID>19040713</NAME_ID>
      <RESORT3>22974</RESORT3>
      <ROOM_STATUS>DI</ROOM_STATUS>
      <TRAVEL_AGENT_ID>63713</TRAVEL_AGENT_ID>
      <SOURCE_ID></SOURCE_ID>
      <RESV_NAME_ID>24337650</RESV_NAME_ID>
      <RM_ADULTS>2</RM_ADULTS>
      <RM_CHILDREN>0</RM_CHILDREN>
      <FULL_NAME>Acosta,Leonardo,Mr.</FULL_NAME>
      <FULL_NAME_NO_SHR_IND>Acosta,Leonardo,Mr.</FULL_NAME_NO_SHR_IND>
      <COMPANY_NAME>T- Scape Travel Marke</COMPANY_NAME>
      <GROUP_NAME></GROUP_NAME>
      <MARKET_CODE>WHD</MARKET_CODE>
      <VIP></VIP>
      <RATE_CODE>WHI.01B</RATE_CODE>
      <ROOM_CATEGORY_LABEL>0KP</ROOM_CATEGORY_LABEL>
      <ROOM>1001</ROOM>
      <NIGHTS>3</NIGHTS>
      <DISCOUNT_REASON_CODE></DISCOUNT_REASON_CODE>
      <BLOCK_CODE></BLOCK_CODE>
      <ORIGIN_OF_BOOKING>TAA</ORIGIN_OF_BOOKING>
      <ROOM_NO>                1001</ROOM_NO>
      <CH></CH>
      <PAYMENT_METHOD>CA</PAYMENT_METHOD>
      <CREDIT_CARD_NO></CREDIT_CARD_NO>
      <CREDIT_CARD_EXP_DATE></CREDIT_CARD_EXP_DATE>
      <SOURCE_COMM>N</SOURCE_COMM>
      <PRODUCTS></PRODUCTS>
      <RM_DISC_AMT></RM_DISC_AMT>
      <RM_DIS_PERCENT></RM_DIS_PERCENT>
      <RM_GROSS_RATE>532.8</RM_GROSS_RATE>
      <RM_NET_ROOM_REVENUE>479.08</RM_NET_ROOM_REVENUE>
      <RM_POT_GROSS_RATE>0</RM_POT_GROSS_RATE>
      <RM_POT_NET_ROOM_REVENUE>0</RM_POT_NET_ROOM_REVENUE>
      <DISCOUNT_REASON_DESC></DISCOUNT_REASON_DESC>
      <PRIMARY_01>1</PRIMARY_01>
      <CHANNEL>MAIL</CHANNEL>
      <LIST_G_RESERVATION_NOTES>
      </LIST_G_RESERVATION_NOTES>
      <LIST_G_PROFILE_NOTES>
      </LIST_G_PROFILE_NOTES>
      <LIST_G_ROUTING_INSTRUCTIONS>
      </LIST_G_ROUTING_INSTRUCTIONS>
      <COMM_YN>Y</COMM_YN>
      <RM_NET_VARIANCE>-479.08</RM_NET_VARIANCE>
      <COUNT_COMMENTS>0</COUNT_COMMENTS>
      <COUNT_RES_COMMENTS>0</COUNT_RES_COMMENTS>
      <COUNT_ROUTING>0</COUNT_ROUTING>
    </G_ROOM>
    <G_ROOM>
      <IS_ACCOMPANYING_YN>N</IS_ACCOMPANYING_YN>
      <SHARE_NAMES></SHARE_NAMES>
      <ACCOMPANYING_NAMES></ACCOMPANYING_NAMES>
      <BOOKED_ROOM_CATEGORY>11811</BOOKED_ROOM_CATEGORY>
      <RECORD_TYPE>RESERVATION</RECORD_TYPE>
      <COMMISIONABLE_YN>N</COMMISIONABLE_YN>
      <ALLOTMENT_HEADER_ID></ALLOTMENT_HEADER_ID>
      <CHAR_ARRIVAL>12-06-21</CHAR_ARRIVAL>
      <CHAR_DEPARTURE>01-06-22</CHAR_DEPARTURE>
      <BEGIN_DATE>12-JUN-21</BEGIN_DATE>
      <END_DATE>01-JUN-22</END_DATE>
      <BOOKED_ROOM_CATEGORY_LABEL>0QP</BOOKED_ROOM_CATEGORY_LABEL>
      <IS_SHARED_YN>N</IS_SHARED_YN>
      <NAME_ID>33216</NAME_ID>
      <RESORT3>22974</RESORT3>
      <ROOM_STATUS>DI</ROOM_STATUS>
      <TRAVEL_AGENT_ID></TRAVEL_AGENT_ID>
      <SOURCE_ID></SOURCE_ID>
      <RESV_NAME_ID>22254153</RESV_NAME_ID>
      <RM_ADULTS>1</RM_ADULTS>
      <RM_CHILDREN>0</RM_CHILDREN>
      <FULL_NAME>Malave Gimon,Alberto,Mr.</FULL_NAME>
      <FULL_NAME_NO_SHR_IND>Malave Gimon,Alberto,Mr.</FULL_NAME_NO_SHR_IND>
      <COMPANY_NAME>C- Wyndham Concorde</COMPANY_NAME>
      <GROUP_NAME></GROUP_NAME>
      <MARKET_CODE>HSU</MARKET_CODE>
      <VIP></VIP>
      <RATE_CODE>HSU</RATE_CODE>
      <ROOM_CATEGORY_LABEL>8HKN</ROOM_CATEGORY_LABEL>
      <ROOM>1002</ROOM>
      <NIGHTS>354</NIGHTS>
      <DISCOUNT_REASON_CODE></DISCOUNT_REASON_CODE>
      <BLOCK_CODE></BLOCK_CODE>
      <ORIGIN_OF_BOOKING>GM</ORIGIN_OF_BOOKING>
      <ROOM_NO>                1002</ROOM_NO>
      <CH>H</CH>
      <PAYMENT_METHOD>CA</PAYMENT_METHOD>
      <CREDIT_CARD_NO></CREDIT_CARD_NO>
      <CREDIT_CARD_EXP_DATE></CREDIT_CARD_EXP_DATE>
      <SOURCE_COMM>N</SOURCE_COMM>
      <PRODUCTS></PRODUCTS>
      <RM_DISC_AMT></RM_DISC_AMT>
      <RM_DIS_PERCENT></RM_DIS_PERCENT>
      <RM_GROSS_RATE>0</RM_GROSS_RATE>
      <RM_NET_ROOM_REVENUE>0</RM_NET_ROOM_REVENUE>
      <RM_POT_GROSS_RATE>0</RM_POT_GROSS_RATE>
      <RM_POT_NET_ROOM_REVENUE>0</RM_POT_NET_ROOM_REVENUE>
      <DISCOUNT_REASON_DESC></DISCOUNT_REASON_DESC>
      <PRIMARY_01>1</PRIMARY_01>
      <CHANNEL>NON</CHANNEL>
      <LIST_G_RESERVATION_NOTES>
      </LIST_G_RESERVATION_NOTES>
      <LIST_G_PROFILE_NOTES>
      </LIST_G_PROFILE_NOTES>
      <LIST_G_ROUTING_INSTRUCTIONS>
      </LIST_G_ROUTING_INSTRUCTIONS>
      <COMM_YN>N</COMM_YN>
      <RM_NET_VARIANCE>0</RM_NET_VARIANCE>
      <COUNT_COMMENTS>0</COUNT_COMMENTS>
      <COUNT_RES_COMMENTS>0</COUNT_RES_COMMENTS>
      <COUNT_ROUTING>0</COUNT_ROUTING>
    </G_ROOM>
    <G_ROOM>
      <IS_ACCOMPANYING_YN>N</IS_ACCOMPANYING_YN>
      <SHARE_NAMES></SHARE_NAMES>
      <ACCOMPANYING_NAMES></ACCOMPANYING_NAMES>
      <BOOKED_ROOM_CATEGORY>10815</BOOKED_ROOM_CATEGORY>
      <RECORD_TYPE>RESERVATION</RECORD_TYPE>
      <COMMISIONABLE_YN>N</COMMISIONABLE_YN>
      <ALLOTMENT_HEADER_ID></ALLOTMENT_HEADER_ID>
      <CHAR_ARRIVAL>27-04-22</CHAR_ARRIVAL>
      <CHAR_DEPARTURE>04-05-22</CHAR_DEPARTURE>
      <BEGIN_DATE>27-APR-22</BEGIN_DATE>
      <END_DATE>04-MAY-22</END_DATE>
      <BOOKED_ROOM_CATEGORY_LABEL>3KN</BOOKED_ROOM_CATEGORY_LABEL>
      <IS_SHARED_YN>N</IS_SHARED_YN>
      <NAME_ID>18819963</NAME_ID>
      <RESORT3>22974</RESORT3>
      <ROOM_STATUS>DI</ROOM_STATUS>
      <TRAVEL_AGENT_ID></TRAVEL_AGENT_ID>
      <SOURCE_ID>18720713</SOURCE_ID>
      <RESV_NAME_ID>24036650</RESV_NAME_ID>
      <RM_ADULTS>3</RM_ADULTS>
      <RM_CHILDREN>1</RM_CHILDREN>
      <FULL_NAME>De Guzman Brice単o,Domongo,Mr.</FULL_NAME>
      <FULL_NAME_NO_SHR_IND>De Guzman Brice単o,Domongo,Mr.</FULL_NAME_NO_SHR_IND>
      <COMPANY_NAME>C- Particular
S- Promo Ventas 2022</COMPANY_NAME>
      <GROUP_NAME></GROUP_NAME>
      <MARKET_CODE>COM</MARKET_CODE>
      <VIP></VIP>
      <RATE_CODE>COMRACK$</RATE_CODE>
      <ROOM_CATEGORY_LABEL>3KN</ROOM_CATEGORY_LABEL>
      <ROOM>1006</ROOM>
      <NIGHTS>7</NIGHTS>
      <DISCOUNT_REASON_CODE></DISCOUNT_REASON_CODE>
      <BLOCK_CODE></BLOCK_CODE>
      <ORIGIN_OF_BOOKING>GST</ORIGIN_OF_BOOKING>
      <ROOM_NO>                1006</ROOM_NO>
      <CH></CH>
      <PAYMENT_METHOD>CA</PAYMENT_METHOD>
      <CREDIT_CARD_NO></CREDIT_CARD_NO>
      <CREDIT_CARD_EXP_DATE></CREDIT_CARD_EXP_DATE>
      <SOURCE_COMM>N</SOURCE_COMM>
      <PRODUCTS></PRODUCTS>
      <RM_DISC_AMT></RM_DISC_AMT>
      <RM_DIS_PERCENT></RM_DIS_PERCENT>
      <RM_GROSS_RATE>1021.2</RM_GROSS_RATE>
      <RM_NET_ROOM_REVENUE>913.75</RM_NET_ROOM_REVENUE>
      <RM_POT_GROSS_RATE>0</RM_POT_GROSS_RATE>
      <RM_POT_NET_ROOM_REVENUE>0</RM_POT_NET_ROOM_REVENUE>
      <DISCOUNT_REASON_DESC></DISCOUNT_REASON_DESC>
      <PRIMARY_01>1</PRIMARY_01>
      <CHANNEL>IN</CHANNEL>
      <LIST_G_RESERVATION_NOTES>
      </LIST_G_RESERVATION_NOTES>
      <LIST_G_PROFILE_NOTES>
      </LIST_G_PROFILE_NOTES>
      <LIST_G_ROUTING_INSTRUCTIONS>
      </LIST_G_ROUTING_INSTRUCTIONS>
      <COMM_YN>N</COMM_YN>
      <RM_NET_VARIANCE>-913.75</RM_NET_VARIANCE>
      <COUNT_COMMENTS>0</COUNT_COMMENTS>
      <COUNT_RES_COMMENTS>0</COUNT_RES_COMMENTS>
      <COUNT_ROUTING>0</COUNT_ROUTING>
    </G_ROOM>
    <G_ROOM>
      <IS_ACCOMPANYING_YN>N</IS_ACCOMPANYING_YN>
      <SHARE_NAMES></SHARE_NAMES>
      <ACCOMPANYING_NAMES></ACCOMPANYING_NAMES>
      <BOOKED_ROOM_CATEGORY>11810</BOOKED_ROOM_CATEGORY>
      <RECORD_TYPE>RESERVATION</RECORD_TYPE>
      <COMMISIONABLE_YN>N</COMMISIONABLE_YN>
      <ALLOTMENT_HEADER_ID></ALLOTMENT_HEADER_ID>
      <CHAR_ARRIVAL>28-04-22</CHAR_ARRIVAL>
      <CHAR_DEPARTURE>01-05-22</CHAR_DEPARTURE>
      <BEGIN_DATE>28-APR-22</BEGIN_DATE>
      <END_DATE>01-MAY-22</END_DATE>
      <BOOKED_ROOM_CATEGORY_LABEL>0KP</BOOKED_ROOM_CATEGORY_LABEL>
      <IS_SHARED_YN>N</IS_SHARED_YN>
      <NAME_ID>9929713</NAME_ID>
      <RESORT3>22974</RESORT3>
      <ROOM_STATUS>DI</ROOM_STATUS>
      <TRAVEL_AGENT_ID></TRAVEL_AGENT_ID>
      <SOURCE_ID></SOURCE_ID>
      <RESV_NAME_ID>24240900</RESV_NAME_ID>
      <RM_ADULTS>2</RM_ADULTS>
      <RM_CHILDREN>0</RM_CHILDREN>
      <FULL_NAME>Garcia,Ivan,Mr.</FULL_NAME>
      <FULL_NAME_NO_SHR_IND>Garcia,Ivan,Mr.</FULL_NAME_NO_SHR_IND>
      <COMPANY_NAME>C- Mini Vacaciones</COMPANY_NAME>
      <GROUP_NAME></GROUP_NAME>
      <MARKET_CODE>PKG</MARKET_CODE>
      <VIP></VIP>
      <RATE_CODE>CNT.03B</RATE_CODE>
      <ROOM_CATEGORY_LABEL>0KP</ROOM_CATEGORY_LABEL>
      <ROOM>1101</ROOM>
      <NIGHTS>3</NIGHTS>
      <DISCOUNT_REASON_CODE></DISCOUNT_REASON_CODE>
      <BLOCK_CODE></BLOCK_CODE>
      <ORIGIN_OF_BOOKING>NON</ORIGIN_OF_BOOKING>
      <ROOM_NO>                1101</ROOM_NO>
      <CH></CH>
      <PAYMENT_METHOD>CA</PAYMENT_METHOD>
      <CREDIT_CARD_NO></CREDIT_CARD_NO>
      <CREDIT_CARD_EXP_DATE></CREDIT_CARD_EXP_DATE>
      <SOURCE_COMM>N</SOURCE_COMM>
      <PRODUCTS></PRODUCTS>
      <RM_DISC_AMT></RM_DISC_AMT>
      <RM_DIS_PERCENT></RM_DIS_PERCENT>
      <RM_GROSS_RATE>190.92</RM_GROSS_RATE>
      <RM_NET_ROOM_REVENUE>137.2</RM_NET_ROOM_REVENUE>
      <RM_POT_GROSS_RATE>0</RM_POT_GROSS_RATE>
      <RM_POT_NET_ROOM_REVENUE>0</RM_POT_NET_ROOM_REVENUE>
      <DISCOUNT_REASON_DESC></DISCOUNT_REASON_DESC>
      <PRIMARY_01>1</PRIMARY_01>
      <CHANNEL>MAIL</CHANNEL>
      <LIST_G_RESERVATION_NOTES>
      </LIST_G_RESERVATION_NOTES>
      <LIST_G_PROFILE_NOTES>
      </LIST_G_PROFILE_NOTES>
      <LIST_G_ROUTING_INSTRUCTIONS>
      </LIST_G_ROUTING_INSTRUCTIONS>
      <COMM_YN>N</COMM_YN>
      <RM_NET_VARIANCE>-137.2</RM_NET_VARIANCE>
      <COUNT_COMMENTS>0</COUNT_COMMENTS>
      <COUNT_RES_COMMENTS>0</COUNT_RES_COMMENTS>
      <COUNT_ROUTING>0</COUNT_ROUTING>
    </G_ROOM>
    <G_ROOM>
      <IS_ACCOMPANYING_YN>N</IS_ACCOMPANYING_YN>
      <SHARE_NAMES></SHARE_NAMES>
      <ACCOMPANYING_NAMES></ACCOMPANYING_NAMES>
      <BOOKED_ROOM_CATEGORY>11810</BOOKED_ROOM_CATEGORY>
      <RECORD_TYPE>RESERVATION</RECORD_TYPE>
      <COMMISIONABLE_YN>N</COMMISIONABLE_YN>
      <ALLOTMENT_HEADER_ID></ALLOTMENT_HEADER_ID>
      <CHAR_ARRIVAL>28-04-22</CHAR_ARRIVAL>
      <CHAR_DEPARTURE>01-05-22</CHAR_DEPARTURE>
      <BEGIN_DATE>28-APR-22</BEGIN_DATE>
      <END_DATE>01-MAY-22</END_DATE>
      <BOOKED_ROOM_CATEGORY_LABEL>0KP</BOOKED_ROOM_CATEGORY_LABEL>
      <IS_SHARED_YN>N</IS_SHARED_YN>
      <NAME_ID>19040963</NAME_ID>
      <RESORT3>22974</RESORT3>
      <ROOM_STATUS>DI</ROOM_STATUS>
      <TRAVEL_AGENT_ID></TRAVEL_AGENT_ID>
      <SOURCE_ID>18720713</SOURCE_ID>
      <RESV_NAME_ID>24339150</RESV_NAME_ID>
      <RM_ADULTS>2</RM_ADULTS>
      <RM_CHILDREN>0</RM_CHILDREN>
      <FULL_NAME>Bouraphed,Tony,Mr.</FULL_NAME>
      <FULL_NAME_NO_SHR_IND>Bouraphed,Tony,Mr.</FULL_NAME_NO_SHR_IND>
      <COMPANY_NAME>C- Particular
S- Promo Ventas 2022</COMPANY_NAME>
      <GROUP_NAME></GROUP_NAME>
      <MARKET_CODE>COM</MARKET_CODE>
      <VIP></VIP>
      <RATE_CODE>COMRACK$</RATE_CODE>
      <ROOM_CATEGORY_LABEL>0KP</ROOM_CATEGORY_LABEL>
      <ROOM>1102</ROOM>
      <NIGHTS>3</NIGHTS>
      <DISCOUNT_REASON_CODE></DISCOUNT_REASON_CODE>
      <BLOCK_CODE></BLOCK_CODE>
      <ORIGIN_OF_BOOKING>GST</ORIGIN_OF_BOOKING>
      <ROOM_NO>                1102</ROOM_NO>
      <CH></CH>
      <PAYMENT_METHOD>CA</PAYMENT_METHOD>
      <CREDIT_CARD_NO></CREDIT_CARD_NO>
      <CREDIT_CARD_EXP_DATE></CREDIT_CARD_EXP_DATE>
      <SOURCE_COMM>N</SOURCE_COMM>
      <PRODUCTS></PRODUCTS>
      <RM_DISC_AMT></RM_DISC_AMT>
      <RM_DIS_PERCENT></RM_DIS_PERCENT>
      <RM_GROSS_RATE>666</RM_GROSS_RATE>
      <RM_NET_ROOM_REVENUE>612.28</RM_NET_ROOM_REVENUE>
      <RM_POT_GROSS_RATE>0</RM_POT_GROSS_RATE>
      <RM_POT_NET_ROOM_REVENUE>0</RM_POT_NET_ROOM_REVENUE>
      <DISCOUNT_REASON_DESC></DISCOUNT_REASON_DESC>
      <PRIMARY_01>1</PRIMARY_01>
      <CHANNEL>IN</CHANNEL>
      <LIST_G_RESERVATION_NOTES>
      </LIST_G_RESERVATION_NOTES>
      <LIST_G_PROFILE_NOTES>
      </LIST_G_PROFILE_NOTES>
      <LIST_G_ROUTING_INSTRUCTIONS>
      </LIST_G_ROUTING_INSTRUCTIONS>
      <COMM_YN>N</COMM_YN>
      <RM_NET_VARIANCE>-612.28</RM_NET_VARIANCE>
      <COUNT_COMMENTS>0</COUNT_COMMENTS>
      <COUNT_RES_COMMENTS>0</COUNT_RES_COMMENTS>
      <COUNT_ROUTING>0</COUNT_ROUTING>
    </G_ROOM>
    <G_ROOM>
      <IS_ACCOMPANYING_YN>N</IS_ACCOMPANYING_YN>
      <SHARE_NAMES></SHARE_NAMES>
      <ACCOMPANYING_NAMES></ACCOMPANYING_NAMES>
      <BOOKED_ROOM_CATEGORY>11810</BOOKED_ROOM_CATEGORY>
      <RECORD_TYPE>RESERVATION</RECORD_TYPE>
      <COMMISIONABLE_YN>N</COMMISIONABLE_YN>
      <ALLOTMENT_HEADER_ID></ALLOTMENT_HEADER_ID>
      <CHAR_ARRIVAL>26-04-22</CHAR_ARRIVAL>
      <CHAR_DEPARTURE>29-04-22</CHAR_DEPARTURE>
      <BEGIN_DATE>26-APR-22</BEGIN_DATE>
      <END_DATE>29-APR-22</END_DATE>
      <BOOKED_ROOM_CATEGORY_LABEL>0KP</BOOKED_ROOM_CATEGORY_LABEL>
      <IS_SHARED_YN>N</IS_SHARED_YN>
      <NAME_ID>18788213</NAME_ID>
      <RESORT3>22974</RESORT3>
      <ROOM_STATUS>DI</ROOM_STATUS>
      <TRAVEL_AGENT_ID></TRAVEL_AGENT_ID>
      <SOURCE_ID></SOURCE_ID>
      <RESV_NAME_ID>23990400</RESV_NAME_ID>
      <RM_ADULTS>2</RM_ADULTS>
      <RM_CHILDREN>0</RM_CHILDREN>
      <FULL_NAME>Varajas,Jesuel,Mr.</FULL_NAME>
      <FULL_NAME_NO_SHR_IND>Varajas,Jesuel,Mr.</FULL_NAME_NO_SHR_IND>
      <COMPANY_NAME>C- Mini Vacaciones</COMPANY_NAME>
      <GROUP_NAME></GROUP_NAME>
      <MARKET_CODE>PKG</MARKET_CODE>
      <VIP></VIP>
      <RATE_CODE>CNT.03B</RATE_CODE>
      <ROOM_CATEGORY_LABEL>0KP</ROOM_CATEGORY_LABEL>
      <ROOM>1104</ROOM>
      <NIGHTS>3</NIGHTS>
      <DISCOUNT_REASON_CODE></DISCOUNT_REASON_CODE>
      <BLOCK_CODE></BLOCK_CODE>
      <ORIGIN_OF_BOOKING>NON</ORIGIN_OF_BOOKING>
      <ROOM_NO>                1104</ROOM_NO>
      <CH></CH>
      <PAYMENT_METHOD>CA</PAYMENT_METHOD>
      <CREDIT_CARD_NO></CREDIT_CARD_NO>
      <CREDIT_CARD_EXP_DATE></CREDIT_CARD_EXP_DATE>
      <SOURCE_COMM>N</SOURCE_COMM>
      <PRODUCTS></PRODUCTS>
      <RM_DISC_AMT></RM_DISC_AMT>
      <RM_DIS_PERCENT></RM_DIS_PERCENT>
      <RM_GROSS_RATE>190.49</RM_GROSS_RATE>
      <RM_NET_ROOM_REVENUE>136.89</RM_NET_ROOM_REVENUE>
      <RM_POT_GROSS_RATE>0</RM_POT_GROSS_RATE>
      <RM_POT_NET_ROOM_REVENUE>0</RM_POT_NET_ROOM_REVENUE>
      <DISCOUNT_REASON_DESC></DISCOUNT_REASON_DESC>
      <PRIMARY_01>1</PRIMARY_01>
      <CHANNEL>MAIL</CHANNEL>
      <LIST_G_RESERVATION_NOTES>
      </LIST_G_RESERVATION_NOTES>
      <LIST_G_PROFILE_NOTES>
      </LIST_G_PROFILE_NOTES>
      <LIST_G_ROUTING_INSTRUCTIONS>
      </LIST_G_ROUTING_INSTRUCTIONS>
      <COMM_YN>N</COMM_YN>
      <RM_NET_VARIANCE>-136.89</RM_NET_VARIANCE>
      <COUNT_COMMENTS>0</COUNT_COMMENTS>
      <COUNT_RES_COMMENTS>0</COUNT_RES_COMMENTS>
      <COUNT_ROUTING>0</COUNT_ROUTING>
    </G_ROOM>
    <G_ROOM>
      <IS_ACCOMPANYING_YN>N</IS_ACCOMPANYING_YN>
      <SHARE_NAMES></SHARE_NAMES>
      <ACCOMPANYING_NAMES></ACCOMPANYING_NAMES>
      <BOOKED_ROOM_CATEGORY>10815</BOOKED_ROOM_CATEGORY>
      <RECORD_TYPE>RESERVATION</RECORD_TYPE>
      <COMMISIONABLE_YN>N</COMMISIONABLE_YN>
      <ALLOTMENT_HEADER_ID></ALLOTMENT_HEADER_ID>
      <CHAR_ARRIVAL>27-04-22</CHAR_ARRIVAL>
      <CHAR_DEPARTURE>30-04-22</CHAR_DEPARTURE>
      <BEGIN_DATE>27-APR-22</BEGIN_DATE>
      <END_DATE>30-APR-22</END_DATE>
      <BOOKED_ROOM_CATEGORY_LABEL>3KN</BOOKED_ROOM_CATEGORY_LABEL>
      <IS_SHARED_YN>N</IS_SHARED_YN>
      <NAME_ID>5968463</NAME_ID>
      <RESORT3>22974</RESORT3>
      <ROOM_STATUS>DI</ROOM_STATUS>
      <TRAVEL_AGENT_ID></TRAVEL_AGENT_ID>
      <SOURCE_ID>18720713</SOURCE_ID>
      <RESV_NAME_ID>24246400</RESV_NAME_ID>
      <RM_ADULTS>5</RM_ADULTS>
      <RM_CHILDREN>0</RM_CHILDREN>
      <FULL_NAME>Russo,Diana,Mrs.</FULL_NAME>
      <FULL_NAME_NO_SHR_IND>Russo,Diana,Mrs.</FULL_NAME_NO_SHR_IND>
      <COMPANY_NAME>C- Particular
S- Promo Ventas 2022</COMPANY_NAME>
      <GROUP_NAME></GROUP_NAME>
      <MARKET_CODE>COM</MARKET_CODE>
      <VIP></VIP>
      <RATE_CODE>COMRACK$</RATE_CODE>
      <ROOM_CATEGORY_LABEL>3KN</ROOM_CATEGORY_LABEL>
      <ROOM>1106</ROOM>
      <NIGHTS>3</NIGHTS>
      <DISCOUNT_REASON_CODE></DISCOUNT_REASON_CODE>
      <BLOCK_CODE></BLOCK_CODE>
      <ORIGIN_OF_BOOKING>GST</ORIGIN_OF_BOOKING>
      <ROOM_NO>                1106</ROOM_NO>
      <CH></CH>
      <PAYMENT_METHOD>CA</PAYMENT_METHOD>
      <CREDIT_CARD_NO></CREDIT_CARD_NO>
      <CREDIT_CARD_EXP_DATE></CREDIT_CARD_EXP_DATE>
      <SOURCE_COMM>N</SOURCE_COMM>
      <PRODUCTS></PRODUCTS>
      <RM_DISC_AMT></RM_DISC_AMT>
      <RM_DIS_PERCENT></RM_DIS_PERCENT>
      <RM_GROSS_RATE>1065.6</RM_GROSS_RATE>
      <RM_NET_ROOM_REVENUE>931.29</RM_NET_ROOM_REVENUE>
      <RM_POT_GROSS_RATE>0</RM_POT_GROSS_RATE>
      <RM_POT_NET_ROOM_REVENUE>0</RM_POT_NET_ROOM_REVENUE>
      <DISCOUNT_REASON_DESC></DISCOUNT_REASON_DESC>
      <PRIMARY_01>1</PRIMARY_01>
      <CHANNEL>MAIL</CHANNEL>
      <LIST_G_RESERVATION_NOTES>
      </LIST_G_RESERVATION_NOTES>
      <LIST_G_PROFILE_NOTES>
      </LIST_G_PROFILE_NOTES>
      <LIST_G_ROUTING_INSTRUCTIONS>
      </LIST_G_ROUTING_INSTRUCTIONS>
      <COMM_YN>N</COMM_YN>
      <RM_NET_VARIANCE>-931.29</RM_NET_VARIANCE>
      <COUNT_COMMENTS>0</COUNT_COMMENTS>
      <COUNT_RES_COMMENTS>0</COUNT_RES_COMMENTS>
      <COUNT_ROUTING>0</COUNT_ROUTING>
    </G_ROOM>
    <G_ROOM>
      <IS_ACCOMPANYING_YN>N</IS_ACCOMPANYING_YN>
      <SHARE_NAMES></SHARE_NAMES>
      <ACCOMPANYING_NAMES></ACCOMPANYING_NAMES>
      <BOOKED_ROOM_CATEGORY>10814</BOOKED_ROOM_CATEGORY>
      <RECORD_TYPE>RESERVATION</RECORD_TYPE>
      <COMMISIONABLE_YN>N</COMMISIONABLE_YN>
      <ALLOTMENT_HEADER_ID></ALLOTMENT_HEADER_ID>
      <CHAR_ARRIVAL>27-04-22</CHAR_ARRIVAL>
      <CHAR_DEPARTURE>01-05-22</CHAR_DEPARTURE>
      <BEGIN_DATE>27-APR-22</BEGIN_DATE>
      <END_DATE>01-MAY-22</END_DATE>
      <BOOKED_ROOM_CATEGORY_LABEL>0QN</BOOKED_ROOM_CATEGORY_LABEL>
      <IS_SHARED_YN>N</IS_SHARED_YN>
      <NAME_ID>18990963</NAME_ID>
      <RESORT3>22974</RESORT3>
      <ROOM_STATUS>DI</ROOM_STATUS>
      <TRAVEL_AGENT_ID>15463</TRAVEL_AGENT_ID>
      <SOURCE_ID></SOURCE_ID>
      <RESV_NAME_ID>24268150</RESV_NAME_ID>
      <RM_ADULTS>2</RM_ADULTS>
      <RM_CHILDREN>0</RM_CHILDREN>
      <FULL_NAME>Gil Urdaneta,Alondra,Ms.</FULL_NAME>
      <FULL_NAME_NO_SHR_IND>Gil Urdaneta,Alondra,Ms.</FULL_NAME_NO_SHR_IND>
      <COMPANY_NAME>T- Viajes Indigo Isla</COMPANY_NAME>
      <GROUP_NAME></GROUP_NAME>
      <MARKET_CODE>WHD</MARKET_CODE>
      <VIP></VIP>
      <RATE_CODE>WHI.01B</RATE_CODE>
      <ROOM_CATEGORY_LABEL>0QN</ROOM_CATEGORY_LABEL>
      <ROOM>1108</ROOM>
      <NIGHTS>4</NIGHTS>
      <DISCOUNT_REASON_CODE></DISCOUNT_REASON_CODE>
      <BLOCK_CODE></BLOCK_CODE>
      <ORIGIN_OF_BOOKING>TAA</ORIGIN_OF_BOOKING>
      <ROOM_NO>                1108</ROOM_NO>
      <CH></CH>
      <PAYMENT_METHOD>CA</PAYMENT_METHOD>
      <CREDIT_CARD_NO></CREDIT_CARD_NO>
      <CREDIT_CARD_EXP_DATE></CREDIT_CARD_EXP_DATE>
      <SOURCE_COMM>N</SOURCE_COMM>
      <PRODUCTS></PRODUCTS>
      <RM_DISC_AMT></RM_DISC_AMT>
      <RM_DIS_PERCENT></RM_DIS_PERCENT>
      <RM_GROSS_RATE>461.76</RM_GROSS_RATE>
      <RM_NET_ROOM_REVENUE>408.04</RM_NET_ROOM_REVENUE>
      <RM_POT_GROSS_RATE>0</RM_POT_GROSS_RATE>
      <RM_POT_NET_ROOM_REVENUE>0</RM_POT_NET_ROOM_REVENUE>
      <DISCOUNT_REASON_DESC></DISCOUNT_REASON_DESC>
      <PRIMARY_01>1</PRIMARY_01>
      <CHANNEL>MAIL</CHANNEL>
      <LIST_G_RESERVATION_NOTES>
      </LIST_G_RESERVATION_NOTES>
      <LIST_G_PROFILE_NOTES>
      </LIST_G_PROFILE_NOTES>
      <LIST_G_ROUTING_INSTRUCTIONS>
      </LIST_G_ROUTING_INSTRUCTIONS>
      <COMM_YN>Y</COMM_YN>
      <RM_NET_VARIANCE>-408.04</RM_NET_VARIANCE>
      <COUNT_COMMENTS>0</COUNT_COMMENTS>
      <COUNT_RES_COMMENTS>0</COUNT_RES_COMMENTS>
      <COUNT_ROUTING>0</COUNT_ROUTING>
    </G_ROOM>
    <G_ROOM>
      <IS_ACCOMPANYING_YN>N</IS_ACCOMPANYING_YN>
      <SHARE_NAMES></SHARE_NAMES>
      <ACCOMPANYING_NAMES></ACCOMPANYING_NAMES>
      <BOOKED_ROOM_CATEGORY>10814</BOOKED_ROOM_CATEGORY>
      <RECORD_TYPE>RESERVATION</RECORD_TYPE>
      <COMMISIONABLE_YN>N</COMMISIONABLE_YN>
      <ALLOTMENT_HEADER_ID></ALLOTMENT_HEADER_ID>
      <CHAR_ARRIVAL>27-04-22</CHAR_ARRIVAL>
      <CHAR_DEPARTURE>01-05-22</CHAR_DEPARTURE>
      <BEGIN_DATE>27-APR-22</BEGIN_DATE>
      <END_DATE>01-MAY-22</END_DATE>
      <BOOKED_ROOM_CATEGORY_LABEL>0QN</BOOKED_ROOM_CATEGORY_LABEL>
      <IS_SHARED_YN>N</IS_SHARED_YN>
      <NAME_ID>18991713</NAME_ID>
      <RESORT3>22974</RESORT3>
      <ROOM_STATUS>DI</ROOM_STATUS>
      <TRAVEL_AGENT_ID>15463</TRAVEL_AGENT_ID>
      <SOURCE_ID></SOURCE_ID>
      <RESV_NAME_ID>24268650</RESV_NAME_ID>
      <RM_ADULTS>3</RM_ADULTS>
      <RM_CHILDREN>0</RM_CHILDREN>
      <FULL_NAME>Gimenez,Jonas Jesus,Mr.</FULL_NAME>
      <FULL_NAME_NO_SHR_IND>Gimenez,Jonas Jesus,Mr.</FULL_NAME_NO_SHR_IND>
      <COMPANY_NAME>T- Viajes Indigo Isla</COMPANY_NAME>
      <GROUP_NAME></GROUP_NAME>
      <MARKET_CODE>WHD</MARKET_CODE>
      <VIP></VIP>
      <RATE_CODE>WHI.01B</RATE_CODE>
      <ROOM_CATEGORY_LABEL>0QN</ROOM_CATEGORY_LABEL>
      <ROOM>1109</ROOM>
      <NIGHTS>4</NIGHTS>
      <DISCOUNT_REASON_CODE></DISCOUNT_REASON_CODE>
      <BLOCK_CODE></BLOCK_CODE>
      <ORIGIN_OF_BOOKING>TAA</ORIGIN_OF_BOOKING>
      <ROOM_NO>                1109</ROOM_NO>
      <CH></CH>
      <PAYMENT_METHOD>CA</PAYMENT_METHOD>
      <CREDIT_CARD_NO></CREDIT_CARD_NO>
      <CREDIT_CARD_EXP_DATE></CREDIT_CARD_EXP_DATE>
      <SOURCE_COMM>N</SOURCE_COMM>
      <PRODUCTS></PRODUCTS>
      <RM_DISC_AMT></RM_DISC_AMT>
      <RM_DIS_PERCENT></RM_DIS_PERCENT>
      <RM_GROSS_RATE>532.8</RM_GROSS_RATE>
      <RM_NET_ROOM_REVENUE>452.21</RM_NET_ROOM_REVENUE>
      <RM_POT_GROSS_RATE>0</RM_POT_GROSS_RATE>
      <RM_POT_NET_ROOM_REVENUE>0</RM_POT_NET_ROOM_REVENUE>
      <DISCOUNT_REASON_DESC></DISCOUNT_REASON_DESC>
      <PRIMARY_01>1</PRIMARY_01>
      <CHANNEL>MAIL</CHANNEL>
      <LIST_G_RESERVATION_NOTES>
      </LIST_G_RESERVATION_NOTES>
      <LIST_G_PROFILE_NOTES>
      </LIST_G_PROFILE_NOTES>
      <LIST_G_ROUTING_INSTRUCTIONS>
      </LIST_G_ROUTING_INSTRUCTIONS>
      <COMM_YN>Y</COMM_YN>
      <RM_NET_VARIANCE>-452.21</RM_NET_VARIANCE>
      <COUNT_COMMENTS>0</COUNT_COMMENTS>
      <COUNT_RES_COMMENTS>0</COUNT_RES_COMMENTS>
      <COUNT_ROUTING>0</COUNT_ROUTING>
    </G_ROOM>
    <G_ROOM>
      <IS_ACCOMPANYING_YN>N</IS_ACCOMPANYING_YN>
      <SHARE_NAMES></SHARE_NAMES>
      <ACCOMPANYING_NAMES></ACCOMPANYING_NAMES>
      <BOOKED_ROOM_CATEGORY>10812</BOOKED_ROOM_CATEGORY>
      <RECORD_TYPE>RESERVATION</RECORD_TYPE>
      <COMMISIONABLE_YN>N</COMMISIONABLE_YN>
      <ALLOTMENT_HEADER_ID></ALLOTMENT_HEADER_ID>
      <CHAR_ARRIVAL>27-04-22</CHAR_ARRIVAL>
      <CHAR_DEPARTURE>01-05-22</CHAR_DEPARTURE>
      <BEGIN_DATE>27-APR-22</BEGIN_DATE>
      <END_DATE>01-MAY-22</END_DATE>
      <BOOKED_ROOM_CATEGORY_LABEL>0KN</BOOKED_ROOM_CATEGORY_LABEL>
      <IS_SHARED_YN>N</IS_SHARED_YN>
      <NAME_ID>13604214</NAME_ID>
      <RESORT3>22974</RESORT3>
      <ROOM_STATUS>DI</ROOM_STATUS>
      <TRAVEL_AGENT_ID>15463</TRAVEL_AGENT_ID>
      <SOURCE_ID></SOURCE_ID>
      <RESV_NAME_ID>24267900</RESV_NAME_ID>
      <RM_ADULTS>2</RM_ADULTS>
      <RM_CHILDREN>0</RM_CHILDREN>
      <FULL_NAME>Castillo,Javier,Mr.</FULL_NAME>
      <FULL_NAME_NO_SHR_IND>Castillo,Javier,Mr.</FULL_NAME_NO_SHR_IND>
      <COMPANY_NAME>T- Viajes Indigo Isla</COMPANY_NAME>
      <GROUP_NAME></GROUP_NAME>
      <MARKET_CODE>WHD</MARKET_CODE>
      <VIP></VIP>
      <RATE_CODE>WHI.01B</RATE_CODE>
      <ROOM_CATEGORY_LABEL>0KN</ROOM_CATEGORY_LABEL>
      <ROOM>1110</ROOM>
      <NIGHTS>4</NIGHTS>
      <DISCOUNT_REASON_CODE></DISCOUNT_REASON_CODE>
      <BLOCK_CODE></BLOCK_CODE>
      <ORIGIN_OF_BOOKING>TAA</ORIGIN_OF_BOOKING>
      <ROOM_NO>                1110</ROOM_NO>
      <CH></CH>
      <PAYMENT_METHOD>CA</PAYMENT_METHOD>
      <CREDIT_CARD_NO></CREDIT_CARD_NO>
      <CREDIT_CARD_EXP_DATE></CREDIT_CARD_EXP_DATE>
      <SOURCE_COMM>N</SOURCE_COMM>
      <PRODUCTS></PRODUCTS>
      <RM_DISC_AMT></RM_DISC_AMT>
      <RM_DIS_PERCENT></RM_DIS_PERCENT>
      <RM_GROSS_RATE>461.76</RM_GROSS_RATE>
      <RM_NET_ROOM_REVENUE>408.04</RM_NET_ROOM_REVENUE>
      <RM_POT_GROSS_RATE>0</RM_POT_GROSS_RATE>
      <RM_POT_NET_ROOM_REVENUE>0</RM_POT_NET_ROOM_REVENUE>
      <DISCOUNT_REASON_DESC></DISCOUNT_REASON_DESC>
      <PRIMARY_01>1</PRIMARY_01>
      <CHANNEL>MAIL</CHANNEL>
      <LIST_G_RESERVATION_NOTES>
      </LIST_G_RESERVATION_NOTES>
      <LIST_G_PROFILE_NOTES>
      </LIST_G_PROFILE_NOTES>
      <LIST_G_ROUTING_INSTRUCTIONS>
      </LIST_G_ROUTING_INSTRUCTIONS>
      <COMM_YN>Y</COMM_YN>
      <RM_NET_VARIANCE>-408.04</RM_NET_VARIANCE>
      <COUNT_COMMENTS>0</COUNT_COMMENTS>
      <COUNT_RES_COMMENTS>0</COUNT_RES_COMMENTS>
      <COUNT_ROUTING>0</COUNT_ROUTING>
    </G_ROOM>
    <G_ROOM>
      <IS_ACCOMPANYING_YN>N</IS_ACCOMPANYING_YN>
      <SHARE_NAMES></SHARE_NAMES>
      <ACCOMPANYING_NAMES></ACCOMPANYING_NAMES>
      <BOOKED_ROOM_CATEGORY>11811</BOOKED_ROOM_CATEGORY>
      <RECORD_TYPE>RESERVATION</RECORD_TYPE>
      <COMMISIONABLE_YN>N</COMMISIONABLE_YN>
      <ALLOTMENT_HEADER_ID></ALLOTMENT_HEADER_ID>
      <CHAR_ARRIVAL>21-04-22</CHAR_ARRIVAL>
      <CHAR_DEPARTURE>29-04-22</CHAR_DEPARTURE>
      <BEGIN_DATE>21-APR-22</BEGIN_DATE>
      <END_DATE>29-APR-22</END_DATE>
      <BOOKED_ROOM_CATEGORY_LABEL>0QP</BOOKED_ROOM_CATEGORY_LABEL>
      <IS_SHARED_YN>N</IS_SHARED_YN>
      <NAME_ID>18989213</NAME_ID>
      <RESORT3>22974</RESORT3>
      <ROOM_STATUS>DI</ROOM_STATUS>
      <TRAVEL_AGENT_ID></TRAVEL_AGENT_ID>
      <SOURCE_ID></SOURCE_ID>
      <RESV_NAME_ID>24266650</RESV_NAME_ID>
      <RM_ADULTS>2</RM_ADULTS>
      <RM_CHILDREN>0</RM_CHILDREN>
      <FULL_NAME>Zakhia,Jack,Mr.</FULL_NAME>
      <FULL_NAME_NO_SHR_IND>Zakhia,Jack,Mr.</FULL_NAME_NO_SHR_IND>
      <COMPANY_NAME>C- Particular</COMPANY_NAME>
      <GROUP_NAME></GROUP_NAME>
      <MARKET_CODE>COM</MARKET_CODE>
      <VIP></VIP>
      <RATE_CODE>COMRACK$</RATE_CODE>
      <ROOM_CATEGORY_LABEL>0QP</ROOM_CATEGORY_LABEL>
      <ROOM>1114</ROOM>
      <NIGHTS>8</NIGHTS>
      <DISCOUNT_REASON_CODE></DISCOUNT_REASON_CODE>
      <BLOCK_CODE></BLOCK_CODE>
      <ORIGIN_OF_BOOKING>GST</ORIGIN_OF_BOOKING>
      <ROOM_NO>                1114</ROOM_NO>
      <CH></CH>
      <PAYMENT_METHOD>CA</PAYMENT_METHOD>
      <CREDIT_CARD_NO></CREDIT_CARD_NO>
      <CREDIT_CARD_EXP_DATE></CREDIT_CARD_EXP_DATE>
      <SOURCE_COMM>N</SOURCE_COMM>
      <PRODUCTS></PRODUCTS>
      <RM_DISC_AMT></RM_DISC_AMT>
      <RM_DIS_PERCENT></RM_DIS_PERCENT>
      <RM_GROSS_RATE>666</RM_GROSS_RATE>
      <RM_NET_ROOM_REVENUE>612.28</RM_NET_ROOM_REVENUE>
      <RM_POT_GROSS_RATE>0</RM_POT_GROSS_RATE>
      <RM_POT_NET_ROOM_REVENUE>0</RM_POT_NET_ROOM_REVENUE>
      <DISCOUNT_REASON_DESC></DISCOUNT_REASON_DESC>
      <PRIMARY_01>1</PRIMARY_01>
      <CHANNEL>IN</CHANNEL>
      <LIST_G_RESERVATION_NOTES>
      </LIST_G_RESERVATION_NOTES>
      <LIST_G_PROFILE_NOTES>
      </LIST_G_PROFILE_NOTES>
      <LIST_G_ROUTING_INSTRUCTIONS>
      </LIST_G_ROUTING_INSTRUCTIONS>
      <COMM_YN>N</COMM_YN>
      <RM_NET_VARIANCE>-612.28</RM_NET_VARIANCE>
      <COUNT_COMMENTS>0</COUNT_COMMENTS>
      <COUNT_RES_COMMENTS>0</COUNT_RES_COMMENTS>
      <COUNT_ROUTING>0</COUNT_ROUTING>
    </G_ROOM>
    <G_ROOM>
      <IS_ACCOMPANYING_YN>N</IS_ACCOMPANYING_YN>
      <SHARE_NAMES></SHARE_NAMES>
      <ACCOMPANYING_NAMES></ACCOMPANYING_NAMES>
      <BOOKED_ROOM_CATEGORY>11811</BOOKED_ROOM_CATEGORY>
      <RECORD_TYPE>RESERVATION</RECORD_TYPE>
      <COMMISIONABLE_YN>N</COMMISIONABLE_YN>
      <ALLOTMENT_HEADER_ID></ALLOTMENT_HEADER_ID>
      <CHAR_ARRIVAL>25-04-22</CHAR_ARRIVAL>
      <CHAR_DEPARTURE>03-05-22</CHAR_DEPARTURE>
      <BEGIN_DATE>25-APR-22</BEGIN_DATE>
      <END_DATE>03-MAY-22</END_DATE>
      <BOOKED_ROOM_CATEGORY_LABEL>0QP</BOOKED_ROOM_CATEGORY_LABEL>
      <IS_SHARED_YN>N</IS_SHARED_YN>
      <NAME_ID>17574463</NAME_ID>
      <RESORT3>22974</RESORT3>
      <ROOM_STATUS>DI</ROOM_STATUS>
      <TRAVEL_AGENT_ID></TRAVEL_AGENT_ID>
      <SOURCE_ID>6940714</SOURCE_ID>
      <RESV_NAME_ID>24296150</RESV_NAME_ID>
      <RM_ADULTS>2</RM_ADULTS>
      <RM_CHILDREN>0</RM_CHILDREN>
      <FULL_NAME>Villamizar,Neil,Mr.</FULL_NAME>
      <FULL_NAME_NO_SHR_IND>Villamizar,Neil,Mr.</FULL_NAME_NO_SHR_IND>
      <COMPANY_NAME>S- Scarpati</COMPANY_NAME>
      <GROUP_NAME></GROUP_NAME>
      <MARKET_CODE>CMP</MARKET_CODE>
      <VIP></VIP>
      <RATE_CODE>CMP</RATE_CODE>
      <ROOM_CATEGORY_LABEL>0QP</ROOM_CATEGORY_LABEL>
      <ROOM>1115</ROOM>
      <NIGHTS>8</NIGHTS>
      <DISCOUNT_REASON_CODE></DISCOUNT_REASON_CODE>
      <BLOCK_CODE></BLOCK_CODE>
      <ORIGIN_OF_BOOKING>GST</ORIGIN_OF_BOOKING>
      <ROOM_NO>                1115</ROOM_NO>
      <CH>C</CH>
      <PAYMENT_METHOD>CA</PAYMENT_METHOD>
      <CREDIT_CARD_NO></CREDIT_CARD_NO>
      <CREDIT_CARD_EXP_DATE></CREDIT_CARD_EXP_DATE>
      <SOURCE_COMM>N</SOURCE_COMM>
      <PRODUCTS></PRODUCTS>
      <RM_DISC_AMT></RM_DISC_AMT>
      <RM_DIS_PERCENT></RM_DIS_PERCENT>
      <RM_GROSS_RATE>0</RM_GROSS_RATE>
      <RM_NET_ROOM_REVENUE>0</RM_NET_ROOM_REVENUE>
      <RM_POT_GROSS_RATE>0</RM_POT_GROSS_RATE>
      <RM_POT_NET_ROOM_REVENUE>0</RM_POT_NET_ROOM_REVENUE>
      <DISCOUNT_REASON_DESC></DISCOUNT_REASON_DESC>
      <PRIMARY_01>1</PRIMARY_01>
      <CHANNEL>IN</CHANNEL>
      <LIST_G_RESERVATION_NOTES>
      </LIST_G_RESERVATION_NOTES>
      <LIST_G_PROFILE_NOTES>
      </LIST_G_PROFILE_NOTES>
      <LIST_G_ROUTING_INSTRUCTIONS>
      </LIST_G_ROUTING_INSTRUCTIONS>
      <COMM_YN>N</COMM_YN>
      <RM_NET_VARIANCE>0</RM_NET_VARIANCE>
      <COUNT_COMMENTS>0</COUNT_COMMENTS>
      <COUNT_RES_COMMENTS>0</COUNT_RES_COMMENTS>
      <COUNT_ROUTING>0</COUNT_ROUTING>
    </G_ROOM>
    <G_ROOM>
      <IS_ACCOMPANYING_YN>N</IS_ACCOMPANYING_YN>
      <SHARE_NAMES></SHARE_NAMES>
      <ACCOMPANYING_NAMES></ACCOMPANYING_NAMES>
      <BOOKED_ROOM_CATEGORY>10815</BOOKED_ROOM_CATEGORY>
      <RECORD_TYPE>RESERVATION</RECORD_TYPE>
      <COMMISIONABLE_YN>N</COMMISIONABLE_YN>
      <ALLOTMENT_HEADER_ID></ALLOTMENT_HEADER_ID>
      <CHAR_ARRIVAL>25-04-22</CHAR_ARRIVAL>
      <CHAR_DEPARTURE>03-05-22</CHAR_DEPARTURE>
      <BEGIN_DATE>25-APR-22</BEGIN_DATE>
      <END_DATE>03-MAY-22</END_DATE>
      <BOOKED_ROOM_CATEGORY_LABEL>3KN</BOOKED_ROOM_CATEGORY_LABEL>
      <IS_SHARED_YN>N</IS_SHARED_YN>
      <NAME_ID>18283214</NAME_ID>
      <RESORT3>22974</RESORT3>
      <ROOM_STATUS>DI</ROOM_STATUS>
      <TRAVEL_AGENT_ID></TRAVEL_AGENT_ID>
      <SOURCE_ID>6940714</SOURCE_ID>
      <RESV_NAME_ID>24296151</RESV_NAME_ID>
      <RM_ADULTS>2</RM_ADULTS>
      <RM_CHILDREN>0</RM_CHILDREN>
      <FULL_NAME>Villamizar Velasquez,Neil,Mr.</FULL_NAME>
      <FULL_NAME_NO_SHR_IND>Villamizar Velasquez,Neil,Mr.</FULL_NAME_NO_SHR_IND>
      <COMPANY_NAME>S- Scarpati</COMPANY_NAME>
      <GROUP_NAME></GROUP_NAME>
      <MARKET_CODE>CMP</MARKET_CODE>
      <VIP></VIP>
      <RATE_CODE>CMP</RATE_CODE>
      <ROOM_CATEGORY_LABEL>3KN</ROOM_CATEGORY_LABEL>
      <ROOM>1116</ROOM>
      <NIGHTS>8</NIGHTS>
      <DISCOUNT_REASON_CODE></DISCOUNT_REASON_CODE>
      <BLOCK_CODE></BLOCK_CODE>
      <ORIGIN_OF_BOOKING>GST</ORIGIN_OF_BOOKING>
      <ROOM_NO>                1116</ROOM_NO>
      <CH>C</CH>
      <PAYMENT_METHOD>CA</PAYMENT_METHOD>
      <CREDIT_CARD_NO></CREDIT_CARD_NO>
      <CREDIT_CARD_EXP_DATE></CREDIT_CARD_EXP_DATE>
      <SOURCE_COMM>N</SOURCE_COMM>
      <PRODUCTS></PRODUCTS>
      <RM_DISC_AMT></RM_DISC_AMT>
      <RM_DIS_PERCENT></RM_DIS_PERCENT>
      <RM_GROSS_RATE>0</RM_GROSS_RATE>
      <RM_NET_ROOM_REVENUE>0</RM_NET_ROOM_REVENUE>
      <RM_POT_GROSS_RATE>0</RM_POT_GROSS_RATE>
      <RM_POT_NET_ROOM_REVENUE>0</RM_POT_NET_ROOM_REVENUE>
      <DISCOUNT_REASON_DESC></DISCOUNT_REASON_DESC>
      <PRIMARY_01>1</PRIMARY_01>
      <CHANNEL>IN</CHANNEL>
      <LIST_G_RESERVATION_NOTES>
      </LIST_G_RESERVATION_NOTES>
      <LIST_G_PROFILE_NOTES>
      </LIST_G_PROFILE_NOTES>
      <LIST_G_ROUTING_INSTRUCTIONS>
      </LIST_G_ROUTING_INSTRUCTIONS>
      <COMM_YN>N</COMM_YN>
      <RM_NET_VARIANCE>0</RM_NET_VARIANCE>
      <COUNT_COMMENTS>0</COUNT_COMMENTS>
      <COUNT_RES_COMMENTS>0</COUNT_RES_COMMENTS>
      <COUNT_ROUTING>0</COUNT_ROUTING>
    </G_ROOM>
    <G_ROOM>
      <IS_ACCOMPANYING_YN>N</IS_ACCOMPANYING_YN>
      <SHARE_NAMES></SHARE_NAMES>
      <ACCOMPANYING_NAMES></ACCOMPANYING_NAMES>
      <BOOKED_ROOM_CATEGORY>10812</BOOKED_ROOM_CATEGORY>
      <RECORD_TYPE>RESERVATION</RECORD_TYPE>
      <COMMISIONABLE_YN>N</COMMISIONABLE_YN>
      <ALLOTMENT_HEADER_ID></ALLOTMENT_HEADER_ID>
      <CHAR_ARRIVAL>03-08-21</CHAR_ARRIVAL>
      <CHAR_DEPARTURE>03-08-22</CHAR_DEPARTURE>
      <BEGIN_DATE>03-AUG-21</BEGIN_DATE>
      <END_DATE>03-AUG-22</END_DATE>
      <BOOKED_ROOM_CATEGORY_LABEL>0KN</BOOKED_ROOM_CATEGORY_LABEL>
      <IS_SHARED_YN>N</IS_SHARED_YN>
      <NAME_ID>17656713</NAME_ID>
      <RESORT3>22974</RESORT3>
      <ROOM_STATUS>DI</ROOM_STATUS>
      <TRAVEL_AGENT_ID></TRAVEL_AGENT_ID>
      <SOURCE_ID>6940714</SOURCE_ID>
      <RESV_NAME_ID>22531901</RESV_NAME_ID>
      <RM_ADULTS>2</RM_ADULTS>
      <RM_CHILDREN>0</RM_CHILDREN>
      <FULL_NAME>Blanco,Gustavo,Mrs.</FULL_NAME>
      <FULL_NAME_NO_SHR_IND>Blanco,Gustavo,Mrs.</FULL_NAME_NO_SHR_IND>
      <COMPANY_NAME>S- Scarpati</COMPANY_NAME>
      <GROUP_NAME></GROUP_NAME>
      <MARKET_CODE>CMP</MARKET_CODE>
      <VIP></VIP>
      <RATE_CODE>CMP</RATE_CODE>
      <ROOM_CATEGORY_LABEL>0KN</ROOM_CATEGORY_LABEL>
      <ROOM>1117</ROOM>
      <NIGHTS>365</NIGHTS>
      <DISCOUNT_REASON_CODE></DISCOUNT_REASON_CODE>
      <BLOCK_CODE></BLOCK_CODE>
      <ORIGIN_OF_BOOKING>AMIG</ORIGIN_OF_BOOKING>
      <ROOM_NO>                1117</ROOM_NO>
      <CH>C</CH>
      <PAYMENT_METHOD>CA</PAYMENT_METHOD>
      <CREDIT_CARD_NO></CREDIT_CARD_NO>
      <CREDIT_CARD_EXP_DATE></CREDIT_CARD_EXP_DATE>
      <SOURCE_COMM>N</SOURCE_COMM>
      <PRODUCTS></PRODUCTS>
      <RM_DISC_AMT></RM_DISC_AMT>
      <RM_DIS_PERCENT></RM_DIS_PERCENT>
      <RM_GROSS_RATE>0</RM_GROSS_RATE>
      <RM_NET_ROOM_REVENUE>0</RM_NET_ROOM_REVENUE>
      <RM_POT_GROSS_RATE>0</RM_POT_GROSS_RATE>
      <RM_POT_NET_ROOM_REVENUE>0</RM_POT_NET_ROOM_REVENUE>
      <DISCOUNT_REASON_DESC></DISCOUNT_REASON_DESC>
      <PRIMARY_01>1</PRIMARY_01>
      <CHANNEL>DIR</CHANNEL>
      <LIST_G_RESERVATION_NOTES>
      </LIST_G_RESERVATION_NOTES>
      <LIST_G_PROFILE_NOTES>
      </LIST_G_PROFILE_NOTES>
      <LIST_G_ROUTING_INSTRUCTIONS>
      </LIST_G_ROUTING_INSTRUCTIONS>
      <COMM_YN>N</COMM_YN>
      <RM_NET_VARIANCE>0</RM_NET_VARIANCE>
      <COUNT_COMMENTS>0</COUNT_COMMENTS>
      <COUNT_RES_COMMENTS>0</COUNT_RES_COMMENTS>
      <COUNT_ROUTING>0</COUNT_ROUTING>
    </G_ROOM>
    <G_ROOM>
      <IS_ACCOMPANYING_YN>N</IS_ACCOMPANYING_YN>
      <SHARE_NAMES></SHARE_NAMES>
      <ACCOMPANYING_NAMES></ACCOMPANYING_NAMES>
      <BOOKED_ROOM_CATEGORY>11810</BOOKED_ROOM_CATEGORY>
      <RECORD_TYPE>RESERVATION</RECORD_TYPE>
      <COMMISIONABLE_YN>N</COMMISIONABLE_YN>
      <ALLOTMENT_HEADER_ID></ALLOTMENT_HEADER_ID>
      <CHAR_ARRIVAL>27-04-22</CHAR_ARRIVAL>
      <CHAR_DEPARTURE>01-05-22</CHAR_DEPARTURE>
      <BEGIN_DATE>27-APR-22</BEGIN_DATE>
      <END_DATE>01-MAY-22</END_DATE>
      <BOOKED_ROOM_CATEGORY_LABEL>0KP</BOOKED_ROOM_CATEGORY_LABEL>
      <IS_SHARED_YN>N</IS_SHARED_YN>
      <NAME_ID>17331466</NAME_ID>
      <RESORT3>22974</RESORT3>
      <ROOM_STATUS>DI</ROOM_STATUS>
      <TRAVEL_AGENT_ID>1791464</TRAVEL_AGENT_ID>
      <SOURCE_ID></SOURCE_ID>
      <RESV_NAME_ID>24014900</RESV_NAME_ID>
      <RM_ADULTS>2</RM_ADULTS>
      <RM_CHILDREN>0</RM_CHILDREN>
      <FULL_NAME>Gutierrez Avenda単o,Luis,Mr.</FULL_NAME>
      <FULL_NAME_NO_SHR_IND>Gutierrez Avenda単o,Luis,Mr.</FULL_NAME_NO_SHR_IND>
      <COMPANY_NAME>T- Tucuam C.A.</COMPANY_NAME>
      <GROUP_NAME></GROUP_NAME>
      <MARKET_CODE>WHD</MARKET_CODE>
      <VIP></VIP>
      <RATE_CODE>WHI.01B</RATE_CODE>
      <ROOM_CATEGORY_LABEL>0KP</ROOM_CATEGORY_LABEL>
      <ROOM>1201</ROOM>
      <NIGHTS>4</NIGHTS>
      <DISCOUNT_REASON_CODE></DISCOUNT_REASON_CODE>
      <BLOCK_CODE></BLOCK_CODE>
      <ORIGIN_OF_BOOKING>TAA</ORIGIN_OF_BOOKING>
      <ROOM_NO>                1201</ROOM_NO>
      <CH></CH>
      <PAYMENT_METHOD>CA</PAYMENT_METHOD>
      <CREDIT_CARD_NO></CREDIT_CARD_NO>
      <CREDIT_CARD_EXP_DATE></CREDIT_CARD_EXP_DATE>
      <SOURCE_COMM>N</SOURCE_COMM>
      <PRODUCTS></PRODUCTS>
      <RM_DISC_AMT></RM_DISC_AMT>
      <RM_DIS_PERCENT></RM_DIS_PERCENT>
      <RM_GROSS_RATE>532.8</RM_GROSS_RATE>
      <RM_NET_ROOM_REVENUE>479.08</RM_NET_ROOM_REVENUE>
      <RM_POT_GROSS_RATE>0</RM_POT_GROSS_RATE>
      <RM_POT_NET_ROOM_REVENUE>0</RM_POT_NET_ROOM_REVENUE>
      <DISCOUNT_REASON_DESC></DISCOUNT_REASON_DESC>
      <PRIMARY_01>1</PRIMARY_01>
      <CHANNEL>MAIL</CHANNEL>
      <LIST_G_RESERVATION_NOTES>
      </LIST_G_RESERVATION_NOTES>
      <LIST_G_PROFILE_NOTES>
      </LIST_G_PROFILE_NOTES>
      <LIST_G_ROUTING_INSTRUCTIONS>
      </LIST_G_ROUTING_INSTRUCTIONS>
      <COMM_YN>Y</COMM_YN>
      <RM_NET_VARIANCE>-479.08</RM_NET_VARIANCE>
      <COUNT_COMMENTS>0</COUNT_COMMENTS>
      <COUNT_RES_COMMENTS>0</COUNT_RES_COMMENTS>
      <COUNT_ROUTING>0</COUNT_ROUTING>
    </G_ROOM>
    <G_ROOM>
      <IS_ACCOMPANYING_YN>N</IS_ACCOMPANYING_YN>
      <SHARE_NAMES></SHARE_NAMES>
      <ACCOMPANYING_NAMES></ACCOMPANYING_NAMES>
      <BOOKED_ROOM_CATEGORY>11811</BOOKED_ROOM_CATEGORY>
      <RECORD_TYPE>RESERVATION</RECORD_TYPE>
      <COMMISIONABLE_YN>N</COMMISIONABLE_YN>
      <ALLOTMENT_HEADER_ID></ALLOTMENT_HEADER_ID>
      <CHAR_ARRIVAL>27-04-22</CHAR_ARRIVAL>
      <CHAR_DEPARTURE>01-05-22</CHAR_DEPARTURE>
      <BEGIN_DATE>27-APR-22</BEGIN_DATE>
      <END_DATE>01-MAY-22</END_DATE>
      <BOOKED_ROOM_CATEGORY_LABEL>0QP</BOOKED_ROOM_CATEGORY_LABEL>
      <IS_SHARED_YN>N</IS_SHARED_YN>
      <NAME_ID>19008963</NAME_ID>
      <RESORT3>22974</RESORT3>
      <ROOM_STATUS>DI</ROOM_STATUS>
      <TRAVEL_AGENT_ID></TRAVEL_AGENT_ID>
      <SOURCE_ID>18720713</SOURCE_ID>
      <RESV_NAME_ID>24291650</RESV_NAME_ID>
      <RM_ADULTS>3</RM_ADULTS>
      <RM_CHILDREN>0</RM_CHILDREN>
      <FULL_NAME>Ynsignarez,Evelyn isabel,Mrs.</FULL_NAME>
      <FULL_NAME_NO_SHR_IND>Ynsignarez,Evelyn isabel,Mrs.</FULL_NAME_NO_SHR_IND>
      <COMPANY_NAME>C- Particular
S- Promo Ventas 2022</COMPANY_NAME>
      <GROUP_NAME></GROUP_NAME>
      <MARKET_CODE>COM</MARKET_CODE>
      <VIP></VIP>
      <RATE_CODE>COMRACK$</RATE_CODE>
      <ROOM_CATEGORY_LABEL>0QP</ROOM_CATEGORY_LABEL>
      <ROOM>1205</ROOM>
      <NIGHTS>4</NIGHTS>
      <DISCOUNT_REASON_CODE></DISCOUNT_REASON_CODE>
      <BLOCK_CODE></BLOCK_CODE>
      <ORIGIN_OF_BOOKING>GST</ORIGIN_OF_BOOKING>
      <ROOM_NO>                1205</ROOM_NO>
      <CH></CH>
      <PAYMENT_METHOD>CA</PAYMENT_METHOD>
      <CREDIT_CARD_NO></CREDIT_CARD_NO>
      <CREDIT_CARD_EXP_DATE></CREDIT_CARD_EXP_DATE>
      <SOURCE_COMM>N</SOURCE_COMM>
      <PRODUCTS></PRODUCTS>
      <RM_DISC_AMT></RM_DISC_AMT>
      <RM_DIS_PERCENT></RM_DIS_PERCENT>
      <RM_GROSS_RATE>754.8</RM_GROSS_RATE>
      <RM_NET_ROOM_REVENUE>674.21</RM_NET_ROOM_REVENUE>
      <RM_POT_GROSS_RATE>0</RM_POT_GROSS_RATE>
      <RM_POT_NET_ROOM_REVENUE>0</RM_POT_NET_ROOM_REVENUE>
      <DISCOUNT_REASON_DESC></DISCOUNT_REASON_DESC>
      <PRIMARY_01>1</PRIMARY_01>
      <CHANNEL>MAIL</CHANNEL>
      <LIST_G_RESERVATION_NOTES>
      </LIST_G_RESERVATION_NOTES>
      <LIST_G_PROFILE_NOTES>
      </LIST_G_PROFILE_NOTES>
      <LIST_G_ROUTING_INSTRUCTIONS>
      </LIST_G_ROUTING_INSTRUCTIONS>
      <COMM_YN>N</COMM_YN>
      <RM_NET_VARIANCE>-674.21</RM_NET_VARIANCE>
      <COUNT_COMMENTS>0</COUNT_COMMENTS>
      <COUNT_RES_COMMENTS>0</COUNT_RES_COMMENTS>
      <COUNT_ROUTING>0</COUNT_ROUTING>
    </G_ROOM>
    <G_ROOM>
      <IS_ACCOMPANYING_YN>N</IS_ACCOMPANYING_YN>
      <SHARE_NAMES></SHARE_NAMES>
      <ACCOMPANYING_NAMES></ACCOMPANYING_NAMES>
      <BOOKED_ROOM_CATEGORY>10812</BOOKED_ROOM_CATEGORY>
      <RECORD_TYPE>RESERVATION</RECORD_TYPE>
      <COMMISIONABLE_YN>N</COMMISIONABLE_YN>
      <ALLOTMENT_HEADER_ID></ALLOTMENT_HEADER_ID>
      <CHAR_ARRIVAL>27-04-22</CHAR_ARRIVAL>
      <CHAR_DEPARTURE>29-04-22</CHAR_DEPARTURE>
      <BEGIN_DATE>27-APR-22</BEGIN_DATE>
      <END_DATE>29-APR-22</END_DATE>
      <BOOKED_ROOM_CATEGORY_LABEL>0KN</BOOKED_ROOM_CATEGORY_LABEL>
      <IS_SHARED_YN>N</IS_SHARED_YN>
      <NAME_ID>173213</NAME_ID>
      <RESORT3>22974</RESORT3>
      <ROOM_STATUS>DI</ROOM_STATUS>
      <TRAVEL_AGENT_ID></TRAVEL_AGENT_ID>
      <SOURCE_ID></SOURCE_ID>
      <RESV_NAME_ID>24332650</RESV_NAME_ID>
      <RM_ADULTS>1</RM_ADULTS>
      <RM_CHILDREN>0</RM_CHILDREN>
      <FULL_NAME>Gimenez,Grisel,Mr.</FULL_NAME>
      <FULL_NAME_NO_SHR_IND>Gimenez,Grisel,Mr.</FULL_NAME_NO_SHR_IND>
      <COMPANY_NAME>C- Concorde Margarita</COMPANY_NAME>
      <GROUP_NAME></GROUP_NAME>
      <MARKET_CODE>HSU</MARKET_CODE>
      <VIP>L2</VIP>
      <RATE_CODE>HSU</RATE_CODE>
      <ROOM_CATEGORY_LABEL>0KN</ROOM_CATEGORY_LABEL>
      <ROOM>1211</ROOM>
      <NIGHTS>2</NIGHTS>
      <DISCOUNT_REASON_CODE></DISCOUNT_REASON_CODE>
      <BLOCK_CODE></BLOCK_CODE>
      <ORIGIN_OF_BOOKING>TIME</ORIGIN_OF_BOOKING>
      <ROOM_NO>                1211</ROOM_NO>
      <CH>H</CH>
      <PAYMENT_METHOD>CA</PAYMENT_METHOD>
      <CREDIT_CARD_NO></CREDIT_CARD_NO>
      <CREDIT_CARD_EXP_DATE></CREDIT_CARD_EXP_DATE>
      <SOURCE_COMM>N</SOURCE_COMM>
      <PRODUCTS></PRODUCTS>
      <RM_DISC_AMT></RM_DISC_AMT>
      <RM_DIS_PERCENT></RM_DIS_PERCENT>
      <RM_GROSS_RATE>0</RM_GROSS_RATE>
      <RM_NET_ROOM_REVENUE>0</RM_NET_ROOM_REVENUE>
      <RM_POT_GROSS_RATE>0</RM_POT_GROSS_RATE>
      <RM_POT_NET_ROOM_REVENUE>0</RM_POT_NET_ROOM_REVENUE>
      <DISCOUNT_REASON_DESC></DISCOUNT_REASON_DESC>
      <PRIMARY_01>1</PRIMARY_01>
      <CHANNEL>MAIL</CHANNEL>
      <LIST_G_RESERVATION_NOTES>
      </LIST_G_RESERVATION_NOTES>
      <LIST_G_PROFILE_NOTES>
      </LIST_G_PROFILE_NOTES>
      <LIST_G_ROUTING_INSTRUCTIONS>
      </LIST_G_ROUTING_INSTRUCTIONS>
      <COMM_YN>N</COMM_YN>
      <RM_NET_VARIANCE>0</RM_NET_VARIANCE>
      <COUNT_COMMENTS>0</COUNT_COMMENTS>
      <COUNT_RES_COMMENTS>0</COUNT_RES_COMMENTS>
      <COUNT_ROUTING>0</COUNT_ROUTING>
    </G_ROOM>
    <G_ROOM>
      <IS_ACCOMPANYING_YN>N</IS_ACCOMPANYING_YN>
      <SHARE_NAMES></SHARE_NAMES>
      <ACCOMPANYING_NAMES></ACCOMPANYING_NAMES>
      <BOOKED_ROOM_CATEGORY>11811</BOOKED_ROOM_CATEGORY>
      <RECORD_TYPE>RESERVATION</RECORD_TYPE>
      <COMMISIONABLE_YN>N</COMMISIONABLE_YN>
      <ALLOTMENT_HEADER_ID></ALLOTMENT_HEADER_ID>
      <CHAR_ARRIVAL>28-04-22</CHAR_ARRIVAL>
      <CHAR_DEPARTURE>29-04-22</CHAR_DEPARTURE>
      <BEGIN_DATE>28-APR-22</BEGIN_DATE>
      <END_DATE>29-APR-22</END_DATE>
      <BOOKED_ROOM_CATEGORY_LABEL>0QP</BOOKED_ROOM_CATEGORY_LABEL>
      <IS_SHARED_YN>N</IS_SHARED_YN>
      <NAME_ID>19054213</NAME_ID>
      <RESORT3>22974</RESORT3>
      <ROOM_STATUS>DI</ROOM_STATUS>
      <TRAVEL_AGENT_ID></TRAVEL_AGENT_ID>
      <SOURCE_ID></SOURCE_ID>
      <RESV_NAME_ID>24357400</RESV_NAME_ID>
      <RM_ADULTS>2</RM_ADULTS>
      <RM_CHILDREN>1</RM_CHILDREN>
      <FULL_NAME>Molero,Marian,Mrs.</FULL_NAME>
      <FULL_NAME_NO_SHR_IND>Molero,Marian,Mrs.</FULL_NAME_NO_SHR_IND>
      <COMPANY_NAME>C- Particular</COMPANY_NAME>
      <GROUP_NAME></GROUP_NAME>
      <MARKET_CODE>COM</MARKET_CODE>
      <VIP></VIP>
      <RATE_CODE>COMRACK$</RATE_CODE>
      <ROOM_CATEGORY_LABEL>0QP</ROOM_CATEGORY_LABEL>
      <ROOM>1215</ROOM>
      <NIGHTS>1</NIGHTS>
      <DISCOUNT_REASON_CODE></DISCOUNT_REASON_CODE>
      <BLOCK_CODE></BLOCK_CODE>
      <ORIGIN_OF_BOOKING>WLK</ORIGIN_OF_BOOKING>
      <ROOM_NO>                1215</ROOM_NO>
      <CH></CH>
      <PAYMENT_METHOD>CA</PAYMENT_METHOD>
      <CREDIT_CARD_NO></CREDIT_CARD_NO>
      <CREDIT_CARD_EXP_DATE></CREDIT_CARD_EXP_DATE>
      <SOURCE_COMM>N</SOURCE_COMM>
      <PRODUCTS></PRODUCTS>
      <RM_DISC_AMT></RM_DISC_AMT>
      <RM_DIS_PERCENT></RM_DIS_PERCENT>
      <RM_GROSS_RATE>710.4</RM_GROSS_RATE>
      <RM_NET_ROOM_REVENUE>629.81</RM_NET_ROOM_REVENUE>
      <RM_POT_GROSS_RATE>0</RM_POT_GROSS_RATE>
      <RM_POT_NET_ROOM_REVENUE>0</RM_POT_NET_ROOM_REVENUE>
      <DISCOUNT_REASON_DESC></DISCOUNT_REASON_DESC>
      <PRIMARY_01>1</PRIMARY_01>
      <CHANNEL>IN</CHANNEL>
      <LIST_G_RESERVATION_NOTES>
      </LIST_G_RESERVATION_NOTES>
      <LIST_G_PROFILE_NOTES>
      </LIST_G_PROFILE_NOTES>
      <LIST_G_ROUTING_INSTRUCTIONS>
      </LIST_G_ROUTING_INSTRUCTIONS>
      <COMM_YN>N</COMM_YN>
      <RM_NET_VARIANCE>-629.81</RM_NET_VARIANCE>
      <COUNT_COMMENTS>0</COUNT_COMMENTS>
      <COUNT_RES_COMMENTS>0</COUNT_RES_COMMENTS>
      <COUNT_ROUTING>0</COUNT_ROUTING>
    </G_ROOM>
    <G_ROOM>
      <IS_ACCOMPANYING_YN>N</IS_ACCOMPANYING_YN>
      <SHARE_NAMES></SHARE_NAMES>
      <ACCOMPANYING_NAMES></ACCOMPANYING_NAMES>
      <BOOKED_ROOM_CATEGORY>10815</BOOKED_ROOM_CATEGORY>
      <RECORD_TYPE>RESERVATION</RECORD_TYPE>
      <COMMISIONABLE_YN>N</COMMISIONABLE_YN>
      <ALLOTMENT_HEADER_ID></ALLOTMENT_HEADER_ID>
      <CHAR_ARRIVAL>16-02-22</CHAR_ARRIVAL>
      <CHAR_DEPARTURE>15-09-22</CHAR_DEPARTURE>
      <BEGIN_DATE>16-FEB-22</BEGIN_DATE>
      <END_DATE>15-SEP-22</END_DATE>
      <BOOKED_ROOM_CATEGORY_LABEL>3KN</BOOKED_ROOM_CATEGORY_LABEL>
      <IS_SHARED_YN>N</IS_SHARED_YN>
      <NAME_ID>16490963</NAME_ID>
      <RESORT3>22974</RESORT3>
      <ROOM_STATUS>DI</ROOM_STATUS>
      <TRAVEL_AGENT_ID></TRAVEL_AGENT_ID>
      <SOURCE_ID>6940714</SOURCE_ID>
      <RESV_NAME_ID>23784900</RESV_NAME_ID>
      <RM_ADULTS>2</RM_ADULTS>
      <RM_CHILDREN>0</RM_CHILDREN>
      <FULL_NAME>Lamanna,Antonio N</FULL_NAME>
      <FULL_NAME_NO_SHR_IND>Lamanna,Antonio N</FULL_NAME_NO_SHR_IND>
      <COMPANY_NAME>C- Wyndham Concorde
S- Scarpati</COMPANY_NAME>
      <GROUP_NAME></GROUP_NAME>
      <MARKET_CODE>HSU</MARKET_CODE>
      <VIP></VIP>
      <RATE_CODE>HSU</RATE_CODE>
      <ROOM_CATEGORY_LABEL>3KN</ROOM_CATEGORY_LABEL>
      <ROOM>1216</ROOM>
      <NIGHTS>211</NIGHTS>
      <DISCOUNT_REASON_CODE></DISCOUNT_REASON_CODE>
      <BLOCK_CODE></BLOCK_CODE>
      <ORIGIN_OF_BOOKING>NON</ORIGIN_OF_BOOKING>
      <ROOM_NO>                1216</ROOM_NO>
      <CH>H</CH>
      <PAYMENT_METHOD>CA</PAYMENT_METHOD>
      <CREDIT_CARD_NO></CREDIT_CARD_NO>
      <CREDIT_CARD_EXP_DATE></CREDIT_CARD_EXP_DATE>
      <SOURCE_COMM>N</SOURCE_COMM>
      <PRODUCTS></PRODUCTS>
      <RM_DISC_AMT></RM_DISC_AMT>
      <RM_DIS_PERCENT></RM_DIS_PERCENT>
      <RM_GROSS_RATE>0</RM_GROSS_RATE>
      <RM_NET_ROOM_REVENUE>0</RM_NET_ROOM_REVENUE>
      <RM_POT_GROSS_RATE>0</RM_POT_GROSS_RATE>
      <RM_POT_NET_ROOM_REVENUE>0</RM_POT_NET_ROOM_REVENUE>
      <DISCOUNT_REASON_DESC></DISCOUNT_REASON_DESC>
      <PRIMARY_01>1</PRIMARY_01>
      <CHANNEL>NON</CHANNEL>
      <LIST_G_RESERVATION_NOTES>
      </LIST_G_RESERVATION_NOTES>
      <LIST_G_PROFILE_NOTES>
      </LIST_G_PROFILE_NOTES>
      <LIST_G_ROUTING_INSTRUCTIONS>
      </LIST_G_ROUTING_INSTRUCTIONS>
      <COMM_YN>N</COMM_YN>
      <RM_NET_VARIANCE>0</RM_NET_VARIANCE>
      <COUNT_COMMENTS>0</COUNT_COMMENTS>
      <COUNT_RES_COMMENTS>0</COUNT_RES_COMMENTS>
      <COUNT_ROUTING>0</COUNT_ROUTING>
    </G_ROOM>
    <G_ROOM>
      <IS_ACCOMPANYING_YN>N</IS_ACCOMPANYING_YN>
      <SHARE_NAMES></SHARE_NAMES>
      <ACCOMPANYING_NAMES></ACCOMPANYING_NAMES>
      <BOOKED_ROOM_CATEGORY>10814</BOOKED_ROOM_CATEGORY>
      <RECORD_TYPE>RESERVATION</RECORD_TYPE>
      <COMMISIONABLE_YN>N</COMMISIONABLE_YN>
      <ALLOTMENT_HEADER_ID></ALLOTMENT_HEADER_ID>
      <CHAR_ARRIVAL>28-04-22</CHAR_ARRIVAL>
      <CHAR_DEPARTURE>02-05-22</CHAR_DEPARTURE>
      <BEGIN_DATE>28-APR-22</BEGIN_DATE>
      <END_DATE>02-MAY-22</END_DATE>
      <BOOKED_ROOM_CATEGORY_LABEL>0QN</BOOKED_ROOM_CATEGORY_LABEL>
      <IS_SHARED_YN>N</IS_SHARED_YN>
      <NAME_ID>19013713</NAME_ID>
      <RESORT3>22974</RESORT3>
      <ROOM_STATUS>DI</ROOM_STATUS>
      <TRAVEL_AGENT_ID></TRAVEL_AGENT_ID>
      <SOURCE_ID>18720713</SOURCE_ID>
      <RESV_NAME_ID>24300900</RESV_NAME_ID>
      <RM_ADULTS>2</RM_ADULTS>
      <RM_CHILDREN>0</RM_CHILDREN>
      <FULL_NAME>Achkhanian,Selin,Mr.</FULL_NAME>
      <FULL_NAME_NO_SHR_IND>Achkhanian,Selin,Mr.</FULL_NAME_NO_SHR_IND>
      <COMPANY_NAME>C- Particular
S- Promo Ventas 2022</COMPANY_NAME>
      <GROUP_NAME></GROUP_NAME>
      <MARKET_CODE>COM</MARKET_CODE>
      <VIP></VIP>
      <RATE_CODE>COMRACK$</RATE_CODE>
      <ROOM_CATEGORY_LABEL>0QN</ROOM_CATEGORY_LABEL>
      <ROOM>1220</ROOM>
      <NIGHTS>4</NIGHTS>
      <DISCOUNT_REASON_CODE></DISCOUNT_REASON_CODE>
      <BLOCK_CODE></BLOCK_CODE>
      <ORIGIN_OF_BOOKING>GST</ORIGIN_OF_BOOKING>
      <ROOM_NO>                1220</ROOM_NO>
      <CH></CH>
      <PAYMENT_METHOD>CA</PAYMENT_METHOD>
      <CREDIT_CARD_NO></CREDIT_CARD_NO>
      <CREDIT_CARD_EXP_DATE></CREDIT_CARD_EXP_DATE>
      <SOURCE_COMM>N</SOURCE_COMM>
      <PRODUCTS></PRODUCTS>
      <RM_DISC_AMT></RM_DISC_AMT>
      <RM_DIS_PERCENT></RM_DIS_PERCENT>
      <RM_GROSS_RATE>577.2</RM_GROSS_RATE>
      <RM_NET_ROOM_REVENUE>523.48</RM_NET_ROOM_REVENUE>
      <RM_POT_GROSS_RATE>0</RM_POT_GROSS_RATE>
      <RM_POT_NET_ROOM_REVENUE>0</RM_POT_NET_ROOM_REVENUE>
      <DISCOUNT_REASON_DESC></DISCOUNT_REASON_DESC>
      <PRIMARY_01>1</PRIMARY_01>
      <CHANNEL>IN</CHANNEL>
      <LIST_G_RESERVATION_NOTES>
      </LIST_G_RESERVATION_NOTES>
      <LIST_G_PROFILE_NOTES>
      </LIST_G_PROFILE_NOTES>
      <LIST_G_ROUTING_INSTRUCTIONS>
      </LIST_G_ROUTING_INSTRUCTIONS>
      <COMM_YN>N</COMM_YN>
      <RM_NET_VARIANCE>-523.48</RM_NET_VARIANCE>
      <COUNT_COMMENTS>0</COUNT_COMMENTS>
      <COUNT_RES_COMMENTS>0</COUNT_RES_COMMENTS>
      <COUNT_ROUTING>0</COUNT_ROUTING>
    </G_ROOM>
    <G_ROOM>
      <IS_ACCOMPANYING_YN>N</IS_ACCOMPANYING_YN>
      <SHARE_NAMES></SHARE_NAMES>
      <ACCOMPANYING_NAMES></ACCOMPANYING_NAMES>
      <BOOKED_ROOM_CATEGORY>11810</BOOKED_ROOM_CATEGORY>
      <RECORD_TYPE>RESERVATION</RECORD_TYPE>
      <COMMISIONABLE_YN>N</COMMISIONABLE_YN>
      <ALLOTMENT_HEADER_ID></ALLOTMENT_HEADER_ID>
      <CHAR_ARRIVAL>21-04-22</CHAR_ARRIVAL>
      <CHAR_DEPARTURE>29-04-22</CHAR_DEPARTURE>
      <BEGIN_DATE>21-APR-22</BEGIN_DATE>
      <END_DATE>29-APR-22</END_DATE>
      <BOOKED_ROOM_CATEGORY_LABEL>0KP</BOOKED_ROOM_CATEGORY_LABEL>
      <IS_SHARED_YN>N</IS_SHARED_YN>
      <NAME_ID>18376213</NAME_ID>
      <RESORT3>22974</RESORT3>
      <ROOM_STATUS>DI</ROOM_STATUS>
      <TRAVEL_AGENT_ID></TRAVEL_AGENT_ID>
      <SOURCE_ID>6552213</SOURCE_ID>
      <RESV_NAME_ID>23930400</RESV_NAME_ID>
      <RM_ADULTS>1</RM_ADULTS>
      <RM_CHILDREN>0</RM_CHILDREN>
      <FULL_NAME>KORENEV,VLADIMIR,Mr.</FULL_NAME>
      <FULL_NAME_NO_SHR_IND>KORENEV,VLADIMIR,Mr.</FULL_NAME_NO_SHR_IND>
      <COMPANY_NAME>C- TEZ TOUR
S- Mercado Internacio</COMPANY_NAME>
      <GROUP_NAME></GROUP_NAME>
      <MARKET_CODE>WHI</MARKET_CODE>
      <VIP></VIP>
      <RATE_CODE>WHI01AID</RATE_CODE>
      <ROOM_CATEGORY_LABEL>0KP</ROOM_CATEGORY_LABEL>
      <ROOM>1301</ROOM>
      <NIGHTS>8</NIGHTS>
      <DISCOUNT_REASON_CODE></DISCOUNT_REASON_CODE>
      <BLOCK_CODE></BLOCK_CODE>
      <ORIGIN_OF_BOOKING>TAA</ORIGIN_OF_BOOKING>
      <ROOM_NO>                1301</ROOM_NO>
      <CH></CH>
      <PAYMENT_METHOD>CA</PAYMENT_METHOD>
      <CREDIT_CARD_NO></CREDIT_CARD_NO>
      <CREDIT_CARD_EXP_DATE></CREDIT_CARD_EXP_DATE>
      <SOURCE_COMM>N</SOURCE_COMM>
      <PRODUCTS></PRODUCTS>
      <RM_DISC_AMT></RM_DISC_AMT>
      <RM_DIS_PERCENT></RM_DIS_PERCENT>
      <RM_GROSS_RATE>283.52</RM_GROSS_RATE>
      <RM_NET_ROOM_REVENUE>283.52</RM_NET_ROOM_REVENUE>
      <RM_POT_GROSS_RATE>0</RM_POT_GROSS_RATE>
      <RM_POT_NET_ROOM_REVENUE>0</RM_POT_NET_ROOM_REVENUE>
      <DISCOUNT_REASON_DESC></DISCOUNT_REASON_DESC>
      <PRIMARY_01>1</PRIMARY_01>
      <CHANNEL>MAIL</CHANNEL>
      <LIST_G_RESERVATION_NOTES>
      </LIST_G_RESERVATION_NOTES>
      <LIST_G_PROFILE_NOTES>
      </LIST_G_PROFILE_NOTES>
      <LIST_G_ROUTING_INSTRUCTIONS>
      </LIST_G_ROUTING_INSTRUCTIONS>
      <COMM_YN>N</COMM_YN>
      <RM_NET_VARIANCE>-283.52</RM_NET_VARIANCE>
      <COUNT_COMMENTS>0</COUNT_COMMENTS>
      <COUNT_RES_COMMENTS>0</COUNT_RES_COMMENTS>
      <COUNT_ROUTING>0</COUNT_ROUTING>
    </G_ROOM>
    <G_ROOM>
      <IS_ACCOMPANYING_YN>N</IS_ACCOMPANYING_YN>
      <SHARE_NAMES></SHARE_NAMES>
      <ACCOMPANYING_NAMES></ACCOMPANYING_NAMES>
      <BOOKED_ROOM_CATEGORY>11811</BOOKED_ROOM_CATEGORY>
      <RECORD_TYPE>RESERVATION</RECORD_TYPE>
      <COMMISIONABLE_YN>N</COMMISIONABLE_YN>
      <ALLOTMENT_HEADER_ID></ALLOTMENT_HEADER_ID>
      <CHAR_ARRIVAL>25-04-22</CHAR_ARRIVAL>
      <CHAR_DEPARTURE>30-04-22</CHAR_DEPARTURE>
      <BEGIN_DATE>25-APR-22</BEGIN_DATE>
      <END_DATE>30-APR-22</END_DATE>
      <BOOKED_ROOM_CATEGORY_LABEL>0QP</BOOKED_ROOM_CATEGORY_LABEL>
      <IS_SHARED_YN>N</IS_SHARED_YN>
      <NAME_ID>18715963</NAME_ID>
      <RESORT3>22974</RESORT3>
      <ROOM_STATUS>DI</ROOM_STATUS>
      <TRAVEL_AGENT_ID></TRAVEL_AGENT_ID>
      <SOURCE_ID></SOURCE_ID>
      <RESV_NAME_ID>23890150</RESV_NAME_ID>
      <RM_ADULTS>3</RM_ADULTS>
      <RM_CHILDREN>0</RM_CHILDREN>
      <FULL_NAME>Martinez Garc鱈a,Victor,Mr.</FULL_NAME>
      <FULL_NAME_NO_SHR_IND>Martinez Garc鱈a,Victor,Mr.</FULL_NAME_NO_SHR_IND>
      <COMPANY_NAME>C- Particular</COMPANY_NAME>
      <GROUP_NAME></GROUP_NAME>
      <MARKET_CODE>COM</MARKET_CODE>
      <VIP></VIP>
      <RATE_CODE>COMRACK$</RATE_CODE>
      <ROOM_CATEGORY_LABEL>0QP</ROOM_CATEGORY_LABEL>
      <ROOM>1303</ROOM>
      <NIGHTS>5</NIGHTS>
      <DISCOUNT_REASON_CODE></DISCOUNT_REASON_CODE>
      <BLOCK_CODE></BLOCK_CODE>
      <ORIGIN_OF_BOOKING>GST</ORIGIN_OF_BOOKING>
      <ROOM_NO>                1303</ROOM_NO>
      <CH></CH>
      <PAYMENT_METHOD>CA</PAYMENT_METHOD>
      <CREDIT_CARD_NO></CREDIT_CARD_NO>
      <CREDIT_CARD_EXP_DATE></CREDIT_CARD_EXP_DATE>
      <SOURCE_COMM>N</SOURCE_COMM>
      <PRODUCTS></PRODUCTS>
      <RM_DISC_AMT></RM_DISC_AMT>
      <RM_DIS_PERCENT></RM_DIS_PERCENT>
      <RM_GROSS_RATE>735.38</RM_GROSS_RATE>
      <RM_NET_ROOM_REVENUE>654.98</RM_NET_ROOM_REVENUE>
      <RM_POT_GROSS_RATE>0</RM_POT_GROSS_RATE>
      <RM_POT_NET_ROOM_REVENUE>0</RM_POT_NET_ROOM_REVENUE>
      <DISCOUNT_REASON_DESC></DISCOUNT_REASON_DESC>
      <PRIMARY_01>1</PRIMARY_01>
      <CHANNEL>IN</CHANNEL>
      <LIST_G_RESERVATION_NOTES>
      </LIST_G_RESERVATION_NOTES>
      <LIST_G_PROFILE_NOTES>
      </LIST_G_PROFILE_NOTES>
      <LIST_G_ROUTING_INSTRUCTIONS>
      </LIST_G_ROUTING_INSTRUCTIONS>
      <COMM_YN>N</COMM_YN>
      <RM_NET_VARIANCE>-654.98</RM_NET_VARIANCE>
      <COUNT_COMMENTS>0</COUNT_COMMENTS>
      <COUNT_RES_COMMENTS>0</COUNT_RES_COMMENTS>
      <COUNT_ROUTING>0</COUNT_ROUTING>
    </G_ROOM>
    <G_ROOM>
      <IS_ACCOMPANYING_YN>N</IS_ACCOMPANYING_YN>
      <SHARE_NAMES></SHARE_NAMES>
      <ACCOMPANYING_NAMES></ACCOMPANYING_NAMES>
      <BOOKED_ROOM_CATEGORY>11810</BOOKED_ROOM_CATEGORY>
      <RECORD_TYPE>RESERVATION</RECORD_TYPE>
      <COMMISIONABLE_YN>N</COMMISIONABLE_YN>
      <ALLOTMENT_HEADER_ID></ALLOTMENT_HEADER_ID>
      <CHAR_ARRIVAL>28-04-22</CHAR_ARRIVAL>
      <CHAR_DEPARTURE>02-05-22</CHAR_DEPARTURE>
      <BEGIN_DATE>28-APR-22</BEGIN_DATE>
      <END_DATE>02-MAY-22</END_DATE>
      <BOOKED_ROOM_CATEGORY_LABEL>0KP</BOOKED_ROOM_CATEGORY_LABEL>
      <IS_SHARED_YN>N</IS_SHARED_YN>
      <NAME_ID>19019713</NAME_ID>
      <RESORT3>22974</RESORT3>
      <ROOM_STATUS>DI</ROOM_STATUS>
      <TRAVEL_AGENT_ID></TRAVEL_AGENT_ID>
      <SOURCE_ID>18720713</SOURCE_ID>
      <RESV_NAME_ID>24310901</RESV_NAME_ID>
      <RM_ADULTS>2</RM_ADULTS>
      <RM_CHILDREN>0</RM_CHILDREN>
      <FULL_NAME>Torres,Yurmiris</FULL_NAME>
      <FULL_NAME_NO_SHR_IND>Torres,Yurmiris</FULL_NAME_NO_SHR_IND>
      <COMPANY_NAME>C- Particular
S- Promo Ventas 2022</COMPANY_NAME>
      <GROUP_NAME></GROUP_NAME>
      <MARKET_CODE>COM</MARKET_CODE>
      <VIP></VIP>
      <RATE_CODE>COMRACK$</RATE_CODE>
      <ROOM_CATEGORY_LABEL>0KP</ROOM_CATEGORY_LABEL>
      <ROOM>1304</ROOM>
      <NIGHTS>4</NIGHTS>
      <DISCOUNT_REASON_CODE></DISCOUNT_REASON_CODE>
      <BLOCK_CODE></BLOCK_CODE>
      <ORIGIN_OF_BOOKING>GST</ORIGIN_OF_BOOKING>
      <ROOM_NO>                1304</ROOM_NO>
      <CH></CH>
      <PAYMENT_METHOD>CA</PAYMENT_METHOD>
      <CREDIT_CARD_NO></CREDIT_CARD_NO>
      <CREDIT_CARD_EXP_DATE></CREDIT_CARD_EXP_DATE>
      <SOURCE_COMM>N</SOURCE_COMM>
      <PRODUCTS></PRODUCTS>
      <RM_DISC_AMT></RM_DISC_AMT>
      <RM_DIS_PERCENT></RM_DIS_PERCENT>
      <RM_GROSS_RATE>666</RM_GROSS_RATE>
      <RM_NET_ROOM_REVENUE>612.28</RM_NET_ROOM_REVENUE>
      <RM_POT_GROSS_RATE>0</RM_POT_GROSS_RATE>
      <RM_POT_NET_ROOM_REVENUE>0</RM_POT_NET_ROOM_REVENUE>
      <DISCOUNT_REASON_DESC></DISCOUNT_REASON_DESC>
      <PRIMARY_01>1</PRIMARY_01>
      <CHANNEL>IN</CHANNEL>
      <LIST_G_RESERVATION_NOTES>
      </LIST_G_RESERVATION_NOTES>
      <LIST_G_PROFILE_NOTES>
      </LIST_G_PROFILE_NOTES>
      <LIST_G_ROUTING_INSTRUCTIONS>
      </LIST_G_ROUTING_INSTRUCTIONS>
      <COMM_YN>N</COMM_YN>
      <RM_NET_VARIANCE>-612.28</RM_NET_VARIANCE>
      <COUNT_COMMENTS>0</COUNT_COMMENTS>
      <COUNT_RES_COMMENTS>0</COUNT_RES_COMMENTS>
      <COUNT_ROUTING>0</COUNT_ROUTING>
    </G_ROOM>
    <G_ROOM>
      <IS_ACCOMPANYING_YN>N</IS_ACCOMPANYING_YN>
      <SHARE_NAMES></SHARE_NAMES>
      <ACCOMPANYING_NAMES></ACCOMPANYING_NAMES>
      <BOOKED_ROOM_CATEGORY>10814</BOOKED_ROOM_CATEGORY>
      <RECORD_TYPE>RESERVATION</RECORD_TYPE>
      <COMMISIONABLE_YN>N</COMMISIONABLE_YN>
      <ALLOTMENT_HEADER_ID></ALLOTMENT_HEADER_ID>
      <CHAR_ARRIVAL>28-04-22</CHAR_ARRIVAL>
      <CHAR_DEPARTURE>01-05-22</CHAR_DEPARTURE>
      <BEGIN_DATE>28-APR-22</BEGIN_DATE>
      <END_DATE>01-MAY-22</END_DATE>
      <BOOKED_ROOM_CATEGORY_LABEL>0QN</BOOKED_ROOM_CATEGORY_LABEL>
      <IS_SHARED_YN>N</IS_SHARED_YN>
      <NAME_ID>18814463</NAME_ID>
      <RESORT3>22974</RESORT3>
      <ROOM_STATUS>DI</ROOM_STATUS>
      <TRAVEL_AGENT_ID></TRAVEL_AGENT_ID>
      <SOURCE_ID></SOURCE_ID>
      <RESV_NAME_ID>24028400</RESV_NAME_ID>
      <RM_ADULTS>2</RM_ADULTS>
      <RM_CHILDREN>1</RM_CHILDREN>
      <FULL_NAME>Naddaf Duarte,Faez Gabriel,Mr.</FULL_NAME>
      <FULL_NAME_NO_SHR_IND>Naddaf Duarte,Faez Gabriel,Mr.</FULL_NAME_NO_SHR_IND>
      <COMPANY_NAME>C- Particular</COMPANY_NAME>
      <GROUP_NAME></GROUP_NAME>
      <MARKET_CODE>COM</MARKET_CODE>
      <VIP></VIP>
      <RATE_CODE>COMRACK$</RATE_CODE>
      <ROOM_CATEGORY_LABEL>0QN</ROOM_CATEGORY_LABEL>
      <ROOM>1309</ROOM>
      <NIGHTS>3</NIGHTS>
      <DISCOUNT_REASON_CODE></DISCOUNT_REASON_CODE>
      <BLOCK_CODE></BLOCK_CODE>
      <ORIGIN_OF_BOOKING>GST</ORIGIN_OF_BOOKING>
      <ROOM_NO>                1309</ROOM_NO>
      <CH></CH>
      <PAYMENT_METHOD>CA</PAYMENT_METHOD>
      <CREDIT_CARD_NO></CREDIT_CARD_NO>
      <CREDIT_CARD_EXP_DATE></CREDIT_CARD_EXP_DATE>
      <SOURCE_COMM>N</SOURCE_COMM>
      <PRODUCTS></PRODUCTS>
      <RM_DISC_AMT></RM_DISC_AMT>
      <RM_DIS_PERCENT></RM_DIS_PERCENT>
      <RM_GROSS_RATE>621.6</RM_GROSS_RATE>
      <RM_NET_ROOM_REVENUE>541.01</RM_NET_ROOM_REVENUE>
      <RM_POT_GROSS_RATE>0</RM_POT_GROSS_RATE>
      <RM_POT_NET_ROOM_REVENUE>0</RM_POT_NET_ROOM_REVENUE>
      <DISCOUNT_REASON_DESC></DISCOUNT_REASON_DESC>
      <PRIMARY_01>1</PRIMARY_01>
      <CHANNEL>IN</CHANNEL>
      <LIST_G_RESERVATION_NOTES>
      </LIST_G_RESERVATION_NOTES>
      <LIST_G_PROFILE_NOTES>
      </LIST_G_PROFILE_NOTES>
      <LIST_G_ROUTING_INSTRUCTIONS>
      </LIST_G_ROUTING_INSTRUCTIONS>
      <COMM_YN>N</COMM_YN>
      <RM_NET_VARIANCE>-541.01</RM_NET_VARIANCE>
      <COUNT_COMMENTS>0</COUNT_COMMENTS>
      <COUNT_RES_COMMENTS>0</COUNT_RES_COMMENTS>
      <COUNT_ROUTING>0</COUNT_ROUTING>
    </G_ROOM>
    <G_ROOM>
      <IS_ACCOMPANYING_YN>N</IS_ACCOMPANYING_YN>
      <SHARE_NAMES></SHARE_NAMES>
      <ACCOMPANYING_NAMES></ACCOMPANYING_NAMES>
      <BOOKED_ROOM_CATEGORY>11811</BOOKED_ROOM_CATEGORY>
      <RECORD_TYPE>RESERVATION</RECORD_TYPE>
      <COMMISIONABLE_YN>N</COMMISIONABLE_YN>
      <ALLOTMENT_HEADER_ID></ALLOTMENT_HEADER_ID>
      <CHAR_ARRIVAL>27-04-22</CHAR_ARRIVAL>
      <CHAR_DEPARTURE>01-05-22</CHAR_DEPARTURE>
      <BEGIN_DATE>27-APR-22</BEGIN_DATE>
      <END_DATE>01-MAY-22</END_DATE>
      <BOOKED_ROOM_CATEGORY_LABEL>0QP</BOOKED_ROOM_CATEGORY_LABEL>
      <IS_SHARED_YN>N</IS_SHARED_YN>
      <NAME_ID>18819463</NAME_ID>
      <RESORT3>22974</RESORT3>
      <ROOM_STATUS>DI</ROOM_STATUS>
      <TRAVEL_AGENT_ID>9451213</TRAVEL_AGENT_ID>
      <SOURCE_ID></SOURCE_ID>
      <RESV_NAME_ID>24036150</RESV_NAME_ID>
      <RM_ADULTS>3</RM_ADULTS>
      <RM_CHILDREN>0</RM_CHILDREN>
      <FULL_NAME>Betancourt,Victor,Mr.</FULL_NAME>
      <FULL_NAME_NO_SHR_IND>Betancourt,Victor,Mr.</FULL_NAME_NO_SHR_IND>
      <COMPANY_NAME>T- Horus Tours Vip</COMPANY_NAME>
      <GROUP_NAME></GROUP_NAME>
      <MARKET_CODE>WHD</MARKET_CODE>
      <VIP></VIP>
      <RATE_CODE>WHI.01B</RATE_CODE>
      <ROOM_CATEGORY_LABEL>0QP</ROOM_CATEGORY_LABEL>
      <ROOM>1313</ROOM>
      <NIGHTS>4</NIGHTS>
      <DISCOUNT_REASON_CODE></DISCOUNT_REASON_CODE>
      <BLOCK_CODE></BLOCK_CODE>
      <ORIGIN_OF_BOOKING>TAA</ORIGIN_OF_BOOKING>
      <ROOM_NO>                1313</ROOM_NO>
      <CH></CH>
      <PAYMENT_METHOD>CA</PAYMENT_METHOD>
      <CREDIT_CARD_NO></CREDIT_CARD_NO>
      <CREDIT_CARD_EXP_DATE></CREDIT_CARD_EXP_DATE>
      <SOURCE_COMM>N</SOURCE_COMM>
      <PRODUCTS></PRODUCTS>
      <RM_DISC_AMT></RM_DISC_AMT>
      <RM_DIS_PERCENT></RM_DIS_PERCENT>
      <RM_GROSS_RATE>603.84</RM_GROSS_RATE>
      <RM_NET_ROOM_REVENUE>523.25</RM_NET_ROOM_REVENUE>
      <RM_POT_GROSS_RATE>0</RM_POT_GROSS_RATE>
      <RM_POT_NET_ROOM_REVENUE>0</RM_POT_NET_ROOM_REVENUE>
      <DISCOUNT_REASON_DESC></DISCOUNT_REASON_DESC>
      <PRIMARY_01>1</PRIMARY_01>
      <CHANNEL>MAIL</CHANNEL>
      <LIST_G_RESERVATION_NOTES>
      </LIST_G_RESERVATION_NOTES>
      <LIST_G_PROFILE_NOTES>
      </LIST_G_PROFILE_NOTES>
      <LIST_G_ROUTING_INSTRUCTIONS>
      </LIST_G_ROUTING_INSTRUCTIONS>
      <COMM_YN>Y</COMM_YN>
      <RM_NET_VARIANCE>-523.25</RM_NET_VARIANCE>
      <COUNT_COMMENTS>0</COUNT_COMMENTS>
      <COUNT_RES_COMMENTS>0</COUNT_RES_COMMENTS>
      <COUNT_ROUTING>0</COUNT_ROUTING>
    </G_ROOM>
    <G_ROOM>
      <IS_ACCOMPANYING_YN>N</IS_ACCOMPANYING_YN>
      <SHARE_NAMES></SHARE_NAMES>
      <ACCOMPANYING_NAMES></ACCOMPANYING_NAMES>
      <BOOKED_ROOM_CATEGORY>11811</BOOKED_ROOM_CATEGORY>
      <RECORD_TYPE>RESERVATION</RECORD_TYPE>
      <COMMISIONABLE_YN>N</COMMISIONABLE_YN>
      <ALLOTMENT_HEADER_ID></ALLOTMENT_HEADER_ID>
      <CHAR_ARRIVAL>29-03-22</CHAR_ARRIVAL>
      <CHAR_DEPARTURE>29-04-22</CHAR_DEPARTURE>
      <BEGIN_DATE>29-MAR-22</BEGIN_DATE>
      <END_DATE>29-APR-22</END_DATE>
      <BOOKED_ROOM_CATEGORY_LABEL>0QP</BOOKED_ROOM_CATEGORY_LABEL>
      <IS_SHARED_YN>N</IS_SHARED_YN>
      <NAME_ID>18817213</NAME_ID>
      <RESORT3>22974</RESORT3>
      <ROOM_STATUS>DI</ROOM_STATUS>
      <TRAVEL_AGENT_ID></TRAVEL_AGENT_ID>
      <SOURCE_ID>18817463</SOURCE_ID>
      <RESV_NAME_ID>24032900</RESV_NAME_ID>
      <RM_ADULTS>2</RM_ADULTS>
      <RM_CHILDREN>0</RM_CHILDREN>
      <FULL_NAME>Bazzi,Jihad,Mr.</FULL_NAME>
      <FULL_NAME_NO_SHR_IND>Bazzi,Jihad,Mr.</FULL_NAME_NO_SHR_IND>
      <COMPANY_NAME>S- Larga Estad鱈a</COMPANY_NAME>
      <GROUP_NAME></GROUP_NAME>
      <MARKET_CODE>COM</MARKET_CODE>
      <VIP></VIP>
      <RATE_CODE>COMRACK30D</RATE_CODE>
      <ROOM_CATEGORY_LABEL>0QP</ROOM_CATEGORY_LABEL>
      <ROOM>1413</ROOM>
      <NIGHTS>31</NIGHTS>
      <DISCOUNT_REASON_CODE></DISCOUNT_REASON_CODE>
      <BLOCK_CODE></BLOCK_CODE>
      <ORIGIN_OF_BOOKING>WLK</ORIGIN_OF_BOOKING>
      <ROOM_NO>                1413</ROOM_NO>
      <CH></CH>
      <PAYMENT_METHOD>CA</PAYMENT_METHOD>
      <CREDIT_CARD_NO></CREDIT_CARD_NO>
      <CREDIT_CARD_EXP_DATE></CREDIT_CARD_EXP_DATE>
      <SOURCE_COMM>N</SOURCE_COMM>
      <PRODUCTS></PRODUCTS>
      <RM_DISC_AMT></RM_DISC_AMT>
      <RM_DIS_PERCENT></RM_DIS_PERCENT>
      <RM_GROSS_RATE>517.97</RM_GROSS_RATE>
      <RM_NET_ROOM_REVENUE>464.25</RM_NET_ROOM_REVENUE>
      <RM_POT_GROSS_RATE>0</RM_POT_GROSS_RATE>
      <RM_POT_NET_ROOM_REVENUE>0</RM_POT_NET_ROOM_REVENUE>
      <DISCOUNT_REASON_DESC></DISCOUNT_REASON_DESC>
      <PRIMARY_01>1</PRIMARY_01>
      <CHANNEL></CHANNEL>
      <LIST_G_RESERVATION_NOTES>
      </LIST_G_RESERVATION_NOTES>
      <LIST_G_PROFILE_NOTES>
      </LIST_G_PROFILE_NOTES>
      <LIST_G_ROUTING_INSTRUCTIONS>
      </LIST_G_ROUTING_INSTRUCTIONS>
      <COMM_YN>N</COMM_YN>
      <RM_NET_VARIANCE>-464.25</RM_NET_VARIANCE>
      <COUNT_COMMENTS>0</COUNT_COMMENTS>
      <COUNT_RES_COMMENTS>0</COUNT_RES_COMMENTS>
      <COUNT_ROUTING>0</COUNT_ROUTING>
    </G_ROOM>
    <G_ROOM>
      <IS_ACCOMPANYING_YN>N</IS_ACCOMPANYING_YN>
      <SHARE_NAMES></SHARE_NAMES>
      <ACCOMPANYING_NAMES></ACCOMPANYING_NAMES>
      <BOOKED_ROOM_CATEGORY>10820</BOOKED_ROOM_CATEGORY>
      <RECORD_TYPE>RESERVATION</RECORD_TYPE>
      <COMMISIONABLE_YN>N</COMMISIONABLE_YN>
      <ALLOTMENT_HEADER_ID></ALLOTMENT_HEADER_ID>
      <CHAR_ARRIVAL>28-04-22</CHAR_ARRIVAL>
      <CHAR_DEPARTURE>01-05-22</CHAR_DEPARTURE>
      <BEGIN_DATE>28-APR-22</BEGIN_DATE>
      <END_DATE>01-MAY-22</END_DATE>
      <BOOKED_ROOM_CATEGORY_LABEL>JDT</BOOKED_ROOM_CATEGORY_LABEL>
      <IS_SHARED_YN>N</IS_SHARED_YN>
      <NAME_ID>18704213</NAME_ID>
      <RESORT3>22974</RESORT3>
      <ROOM_STATUS>DI</ROOM_STATUS>
      <TRAVEL_AGENT_ID></TRAVEL_AGENT_ID>
      <SOURCE_ID></SOURCE_ID>
      <RESV_NAME_ID>23875650</RESV_NAME_ID>
      <RM_ADULTS>2</RM_ADULTS>
      <RM_CHILDREN>0</RM_CHILDREN>
      <FULL_NAME>Arcaya,Marcos,Mr.</FULL_NAME>
      <FULL_NAME_NO_SHR_IND>Arcaya,Marcos,Mr.</FULL_NAME_NO_SHR_IND>
      <COMPANY_NAME>C- Concorde Margarita</COMPANY_NAME>
      <GROUP_NAME>Time Share</GROUP_NAME>
      <MARKET_CODE>CNT</MARKET_CODE>
      <VIP></VIP>
      <RATE_CODE>CNT01B</RATE_CODE>
      <ROOM_CATEGORY_LABEL>JDT</ROOM_CATEGORY_LABEL>
      <ROOM>1607</ROOM>
      <NIGHTS>3</NIGHTS>
      <DISCOUNT_REASON_CODE></DISCOUNT_REASON_CODE>
      <BLOCK_CODE></BLOCK_CODE>
      <ORIGIN_OF_BOOKING>TIME</ORIGIN_OF_BOOKING>
      <ROOM_NO>                1607</ROOM_NO>
      <CH></CH>
      <PAYMENT_METHOD>CA</PAYMENT_METHOD>
      <CREDIT_CARD_NO></CREDIT_CARD_NO>
      <CREDIT_CARD_EXP_DATE></CREDIT_CARD_EXP_DATE>
      <SOURCE_COMM>N</SOURCE_COMM>
      <PRODUCTS></PRODUCTS>
      <RM_DISC_AMT></RM_DISC_AMT>
      <RM_DIS_PERCENT></RM_DIS_PERCENT>
      <RM_GROSS_RATE>0</RM_GROSS_RATE>
      <RM_NET_ROOM_REVENUE>0</RM_NET_ROOM_REVENUE>
      <RM_POT_GROSS_RATE>0</RM_POT_GROSS_RATE>
      <RM_POT_NET_ROOM_REVENUE>0</RM_POT_NET_ROOM_REVENUE>
      <DISCOUNT_REASON_DESC></DISCOUNT_REASON_DESC>
      <PRIMARY_01>1</PRIMARY_01>
      <CHANNEL>MAIL</CHANNEL>
      <LIST_G_RESERVATION_NOTES>
      </LIST_G_RESERVATION_NOTES>
      <LIST_G_PROFILE_NOTES>
      </LIST_G_PROFILE_NOTES>
      <LIST_G_ROUTING_INSTRUCTIONS>
      </LIST_G_ROUTING_INSTRUCTIONS>
      <COMM_YN>N</COMM_YN>
      <RM_NET_VARIANCE>0</RM_NET_VARIANCE>
      <COUNT_COMMENTS>0</COUNT_COMMENTS>
      <COUNT_RES_COMMENTS>0</COUNT_RES_COMMENTS>
      <COUNT_ROUTING>0</COUNT_ROUTING>
    </G_ROOM>
    <G_ROOM>
      <IS_ACCOMPANYING_YN>N</IS_ACCOMPANYING_YN>
      <SHARE_NAMES></SHARE_NAMES>
      <ACCOMPANYING_NAMES></ACCOMPANYING_NAMES>
      <BOOKED_ROOM_CATEGORY>10820</BOOKED_ROOM_CATEGORY>
      <RECORD_TYPE>RESERVATION</RECORD_TYPE>
      <COMMISIONABLE_YN>N</COMMISIONABLE_YN>
      <ALLOTMENT_HEADER_ID></ALLOTMENT_HEADER_ID>
      <CHAR_ARRIVAL>27-04-22</CHAR_ARRIVAL>
      <CHAR_DEPARTURE>01-05-22</CHAR_DEPARTURE>
      <BEGIN_DATE>27-APR-22</BEGIN_DATE>
      <END_DATE>01-MAY-22</END_DATE>
      <BOOKED_ROOM_CATEGORY_LABEL>JDT</BOOKED_ROOM_CATEGORY_LABEL>
      <IS_SHARED_YN>N</IS_SHARED_YN>
      <NAME_ID>18012713</NAME_ID>
      <RESORT3>22974</RESORT3>
      <ROOM_STATUS>DI</ROOM_STATUS>
      <TRAVEL_AGENT_ID></TRAVEL_AGENT_ID>
      <SOURCE_ID></SOURCE_ID>
      <RESV_NAME_ID>24289650</RESV_NAME_ID>
      <RM_ADULTS>2</RM_ADULTS>
      <RM_CHILDREN>0</RM_CHILDREN>
      <FULL_NAME>Martin,Elena,Mrs.</FULL_NAME>
      <FULL_NAME_NO_SHR_IND>Martin,Elena,Mrs.</FULL_NAME_NO_SHR_IND>
      <COMPANY_NAME>C- Concorde Margarita</COMPANY_NAME>
      <GROUP_NAME>Time Share</GROUP_NAME>
      <MARKET_CODE>CNT</MARKET_CODE>
      <VIP></VIP>
      <RATE_CODE>CNT01B</RATE_CODE>
      <ROOM_CATEGORY_LABEL>JDT</ROOM_CATEGORY_LABEL>
      <ROOM>1701</ROOM>
      <NIGHTS>4</NIGHTS>
      <DISCOUNT_REASON_CODE></DISCOUNT_REASON_CODE>
      <BLOCK_CODE></BLOCK_CODE>
      <ORIGIN_OF_BOOKING>TIME</ORIGIN_OF_BOOKING>
      <ROOM_NO>                1701</ROOM_NO>
      <CH></CH>
      <PAYMENT_METHOD>CA</PAYMENT_METHOD>
      <CREDIT_CARD_NO></CREDIT_CARD_NO>
      <CREDIT_CARD_EXP_DATE></CREDIT_CARD_EXP_DATE>
      <SOURCE_COMM>N</SOURCE_COMM>
      <PRODUCTS></PRODUCTS>
      <RM_DISC_AMT></RM_DISC_AMT>
      <RM_DIS_PERCENT></RM_DIS_PERCENT>
      <RM_GROSS_RATE>0</RM_GROSS_RATE>
      <RM_NET_ROOM_REVENUE>0</RM_NET_ROOM_REVENUE>
      <RM_POT_GROSS_RATE>0</RM_POT_GROSS_RATE>
      <RM_POT_NET_ROOM_REVENUE>0</RM_POT_NET_ROOM_REVENUE>
      <DISCOUNT_REASON_DESC></DISCOUNT_REASON_DESC>
      <PRIMARY_01>1</PRIMARY_01>
      <CHANNEL>MAIL</CHANNEL>
      <LIST_G_RESERVATION_NOTES>
      </LIST_G_RESERVATION_NOTES>
      <LIST_G_PROFILE_NOTES>
      </LIST_G_PROFILE_NOTES>
      <LIST_G_ROUTING_INSTRUCTIONS>
      </LIST_G_ROUTING_INSTRUCTIONS>
      <COMM_YN>N</COMM_YN>
      <RM_NET_VARIANCE>0</RM_NET_VARIANCE>
      <COUNT_COMMENTS>0</COUNT_COMMENTS>
      <COUNT_RES_COMMENTS>0</COUNT_RES_COMMENTS>
      <COUNT_ROUTING>0</COUNT_ROUTING>
    </G_ROOM>
    <G_ROOM>
      <IS_ACCOMPANYING_YN>N</IS_ACCOMPANYING_YN>
      <SHARE_NAMES></SHARE_NAMES>
      <ACCOMPANYING_NAMES></ACCOMPANYING_NAMES>
      <BOOKED_ROOM_CATEGORY>10822</BOOKED_ROOM_CATEGORY>
      <RECORD_TYPE>RESERVATION</RECORD_TYPE>
      <COMMISIONABLE_YN>N</COMMISIONABLE_YN>
      <ALLOTMENT_HEADER_ID></ALLOTMENT_HEADER_ID>
      <CHAR_ARRIVAL>22-04-22</CHAR_ARRIVAL>
      <CHAR_DEPARTURE>29-04-22</CHAR_DEPARTURE>
      <BEGIN_DATE>22-APR-22</BEGIN_DATE>
      <END_DATE>29-APR-22</END_DATE>
      <BOOKED_ROOM_CATEGORY_LABEL>FST</BOOKED_ROOM_CATEGORY_LABEL>
      <IS_SHARED_YN>N</IS_SHARED_YN>
      <NAME_ID>19001463</NAME_ID>
      <RESORT3>22974</RESORT3>
      <ROOM_STATUS>DI</ROOM_STATUS>
      <TRAVEL_AGENT_ID></TRAVEL_AGENT_ID>
      <SOURCE_ID></SOURCE_ID>
      <RESV_NAME_ID>24260150</RESV_NAME_ID>
      <RM_ADULTS>4</RM_ADULTS>
      <RM_CHILDREN>2</RM_CHILDREN>
      <FULL_NAME>Espinoza,Milver,Mr.</FULL_NAME>
      <FULL_NAME_NO_SHR_IND>Espinoza,Milver,Mr.</FULL_NAME_NO_SHR_IND>
      <COMPANY_NAME>C- Concorde Margarita</COMPANY_NAME>
      <GROUP_NAME>RCI</GROUP_NAME>
      <MARKET_CODE>CNT</MARKET_CODE>
      <VIP></VIP>
      <RATE_CODE>CNT01B</RATE_CODE>
      <ROOM_CATEGORY_LABEL>FST</ROOM_CATEGORY_LABEL>
      <ROOM>1706</ROOM>
      <NIGHTS>7</NIGHTS>
      <DISCOUNT_REASON_CODE></DISCOUNT_REASON_CODE>
      <BLOCK_CODE></BLOCK_CODE>
      <ORIGIN_OF_BOOKING>TIME</ORIGIN_OF_BOOKING>
      <ROOM_NO>                1706</ROOM_NO>
      <CH></CH>
      <PAYMENT_METHOD>CA</PAYMENT_METHOD>
      <CREDIT_CARD_NO></CREDIT_CARD_NO>
      <CREDIT_CARD_EXP_DATE></CREDIT_CARD_EXP_DATE>
      <SOURCE_COMM>N</SOURCE_COMM>
      <PRODUCTS></PRODUCTS>
      <RM_DISC_AMT></RM_DISC_AMT>
      <RM_DIS_PERCENT></RM_DIS_PERCENT>
      <RM_GROSS_RATE>0</RM_GROSS_RATE>
      <RM_NET_ROOM_REVENUE>0</RM_NET_ROOM_REVENUE>
      <RM_POT_GROSS_RATE>0</RM_POT_GROSS_RATE>
      <RM_POT_NET_ROOM_REVENUE>0</RM_POT_NET_ROOM_REVENUE>
      <DISCOUNT_REASON_DESC></DISCOUNT_REASON_DESC>
      <PRIMARY_01>1</PRIMARY_01>
      <CHANNEL>MAIL</CHANNEL>
      <LIST_G_RESERVATION_NOTES>
      </LIST_G_RESERVATION_NOTES>
      <LIST_G_PROFILE_NOTES>
      </LIST_G_PROFILE_NOTES>
      <LIST_G_ROUTING_INSTRUCTIONS>
      </LIST_G_ROUTING_INSTRUCTIONS>
      <COMM_YN>N</COMM_YN>
      <RM_NET_VARIANCE>0</RM_NET_VARIANCE>
      <COUNT_COMMENTS>0</COUNT_COMMENTS>
      <COUNT_RES_COMMENTS>0</COUNT_RES_COMMENTS>
      <COUNT_ROUTING>0</COUNT_ROUTING>
    </G_ROOM>
    <G_ROOM>
      <IS_ACCOMPANYING_YN>N</IS_ACCOMPANYING_YN>
      <SHARE_NAMES></SHARE_NAMES>
      <ACCOMPANYING_NAMES></ACCOMPANYING_NAMES>
      <BOOKED_ROOM_CATEGORY>10820</BOOKED_ROOM_CATEGORY>
      <RECORD_TYPE>RESERVATION</RECORD_TYPE>
      <COMMISIONABLE_YN>N</COMMISIONABLE_YN>
      <ALLOTMENT_HEADER_ID></ALLOTMENT_HEADER_ID>
      <CHAR_ARRIVAL>24-04-22</CHAR_ARRIVAL>
      <CHAR_DEPARTURE>01-05-22</CHAR_DEPARTURE>
      <BEGIN_DATE>24-APR-22</BEGIN_DATE>
      <END_DATE>01-MAY-22</END_DATE>
      <BOOKED_ROOM_CATEGORY_LABEL>JDT</BOOKED_ROOM_CATEGORY_LABEL>
      <IS_SHARED_YN>N</IS_SHARED_YN>
      <NAME_ID>17391463</NAME_ID>
      <RESORT3>22974</RESORT3>
      <ROOM_STATUS>DI</ROOM_STATUS>
      <TRAVEL_AGENT_ID></TRAVEL_AGENT_ID>
      <SOURCE_ID></SOURCE_ID>
      <RESV_NAME_ID>23944901</RESV_NAME_ID>
      <RM_ADULTS>2</RM_ADULTS>
      <RM_CHILDREN>0</RM_CHILDREN>
      <FULL_NAME>Sanchez,Napoleon,Mr.</FULL_NAME>
      <FULL_NAME_NO_SHR_IND>Sanchez,Napoleon,Mr.</FULL_NAME_NO_SHR_IND>
      <COMPANY_NAME>C- Concorde Margarita</COMPANY_NAME>
      <GROUP_NAME>Time Share</GROUP_NAME>
      <MARKET_CODE>CNT</MARKET_CODE>
      <VIP></VIP>
      <RATE_CODE>CNT01B</RATE_CODE>
      <ROOM_CATEGORY_LABEL>JDT</ROOM_CATEGORY_LABEL>
      <ROOM>1713</ROOM>
      <NIGHTS>7</NIGHTS>
      <DISCOUNT_REASON_CODE></DISCOUNT_REASON_CODE>
      <BLOCK_CODE></BLOCK_CODE>
      <ORIGIN_OF_BOOKING>TIME</ORIGIN_OF_BOOKING>
      <ROOM_NO>                1713</ROOM_NO>
      <CH></CH>
      <PAYMENT_METHOD>CA</PAYMENT_METHOD>
      <CREDIT_CARD_NO></CREDIT_CARD_NO>
      <CREDIT_CARD_EXP_DATE></CREDIT_CARD_EXP_DATE>
      <SOURCE_COMM>N</SOURCE_COMM>
      <PRODUCTS></PRODUCTS>
      <RM_DISC_AMT></RM_DISC_AMT>
      <RM_DIS_PERCENT></RM_DIS_PERCENT>
      <RM_GROSS_RATE>0</RM_GROSS_RATE>
      <RM_NET_ROOM_REVENUE>0</RM_NET_ROOM_REVENUE>
      <RM_POT_GROSS_RATE>0</RM_POT_GROSS_RATE>
      <RM_POT_NET_ROOM_REVENUE>0</RM_POT_NET_ROOM_REVENUE>
      <DISCOUNT_REASON_DESC></DISCOUNT_REASON_DESC>
      <PRIMARY_01>1</PRIMARY_01>
      <CHANNEL>MAIL</CHANNEL>
      <LIST_G_RESERVATION_NOTES>
      </LIST_G_RESERVATION_NOTES>
      <LIST_G_PROFILE_NOTES>
      </LIST_G_PROFILE_NOTES>
      <LIST_G_ROUTING_INSTRUCTIONS>
      </LIST_G_ROUTING_INSTRUCTIONS>
      <COMM_YN>N</COMM_YN>
      <RM_NET_VARIANCE>0</RM_NET_VARIANCE>
      <COUNT_COMMENTS>0</COUNT_COMMENTS>
      <COUNT_RES_COMMENTS>0</COUNT_RES_COMMENTS>
      <COUNT_ROUTING>0</COUNT_ROUTING>
    </G_ROOM>
    <G_ROOM>
      <IS_ACCOMPANYING_YN>N</IS_ACCOMPANYING_YN>
      <SHARE_NAMES></SHARE_NAMES>
      <ACCOMPANYING_NAMES></ACCOMPANYING_NAMES>
      <BOOKED_ROOM_CATEGORY>10820</BOOKED_ROOM_CATEGORY>
      <RECORD_TYPE>RESERVATION</RECORD_TYPE>
      <COMMISIONABLE_YN>N</COMMISIONABLE_YN>
      <ALLOTMENT_HEADER_ID></ALLOTMENT_HEADER_ID>
      <CHAR_ARRIVAL>27-04-22</CHAR_ARRIVAL>
      <CHAR_DEPARTURE>01-05-22</CHAR_DEPARTURE>
      <BEGIN_DATE>27-APR-22</BEGIN_DATE>
      <END_DATE>01-MAY-22</END_DATE>
      <BOOKED_ROOM_CATEGORY_LABEL>JDT</BOOKED_ROOM_CATEGORY_LABEL>
      <IS_SHARED_YN>N</IS_SHARED_YN>
      <NAME_ID>18368713</NAME_ID>
      <RESORT3>22974</RESORT3>
      <ROOM_STATUS>DI</ROOM_STATUS>
      <TRAVEL_AGENT_ID></TRAVEL_AGENT_ID>
      <SOURCE_ID></SOURCE_ID>
      <RESV_NAME_ID>24283150</RESV_NAME_ID>
      <RM_ADULTS>2</RM_ADULTS>
      <RM_CHILDREN>0</RM_CHILDREN>
      <FULL_NAME>Arcila,Vladimir,Mr.</FULL_NAME>
      <FULL_NAME_NO_SHR_IND>Arcila,Vladimir,Mr.</FULL_NAME_NO_SHR_IND>
      <COMPANY_NAME>C- Concorde Margarita</COMPANY_NAME>
      <GROUP_NAME>Time Share</GROUP_NAME>
      <MARKET_CODE>CNT</MARKET_CODE>
      <VIP></VIP>
      <RATE_CODE>CNT01B</RATE_CODE>
      <ROOM_CATEGORY_LABEL>JDT</ROOM_CATEGORY_LABEL>
      <ROOM>1801</ROOM>
      <NIGHTS>4</NIGHTS>
      <DISCOUNT_REASON_CODE></DISCOUNT_REASON_CODE>
      <BLOCK_CODE></BLOCK_CODE>
      <ORIGIN_OF_BOOKING>TIME</ORIGIN_OF_BOOKING>
      <ROOM_NO>                1801</ROOM_NO>
      <CH></CH>
      <PAYMENT_METHOD>CA</PAYMENT_METHOD>
      <CREDIT_CARD_NO></CREDIT_CARD_NO>
      <CREDIT_CARD_EXP_DATE></CREDIT_CARD_EXP_DATE>
      <SOURCE_COMM>N</SOURCE_COMM>
      <PRODUCTS></PRODUCTS>
      <RM_DISC_AMT></RM_DISC_AMT>
      <RM_DIS_PERCENT></RM_DIS_PERCENT>
      <RM_GROSS_RATE>0</RM_GROSS_RATE>
      <RM_NET_ROOM_REVENUE>0</RM_NET_ROOM_REVENUE>
      <RM_POT_GROSS_RATE>0</RM_POT_GROSS_RATE>
      <RM_POT_NET_ROOM_REVENUE>0</RM_POT_NET_ROOM_REVENUE>
      <DISCOUNT_REASON_DESC></DISCOUNT_REASON_DESC>
      <PRIMARY_01>1</PRIMARY_01>
      <CHANNEL>MAIL</CHANNEL>
      <LIST_G_RESERVATION_NOTES>
      </LIST_G_RESERVATION_NOTES>
      <LIST_G_PROFILE_NOTES>
      </LIST_G_PROFILE_NOTES>
      <LIST_G_ROUTING_INSTRUCTIONS>
      </LIST_G_ROUTING_INSTRUCTIONS>
      <COMM_YN>N</COMM_YN>
      <RM_NET_VARIANCE>0</RM_NET_VARIANCE>
      <COUNT_COMMENTS>0</COUNT_COMMENTS>
      <COUNT_RES_COMMENTS>0</COUNT_RES_COMMENTS>
      <COUNT_ROUTING>0</COUNT_ROUTING>
    </G_ROOM>
    <G_ROOM>
      <IS_ACCOMPANYING_YN>N</IS_ACCOMPANYING_YN>
      <SHARE_NAMES></SHARE_NAMES>
      <ACCOMPANYING_NAMES></ACCOMPANYING_NAMES>
      <BOOKED_ROOM_CATEGORY>10820</BOOKED_ROOM_CATEGORY>
      <RECORD_TYPE>RESERVATION</RECORD_TYPE>
      <COMMISIONABLE_YN>N</COMMISIONABLE_YN>
      <ALLOTMENT_HEADER_ID></ALLOTMENT_HEADER_ID>
      <CHAR_ARRIVAL>25-04-22</CHAR_ARRIVAL>
      <CHAR_DEPARTURE>30-04-22</CHAR_DEPARTURE>
      <BEGIN_DATE>25-APR-22</BEGIN_DATE>
      <END_DATE>30-APR-22</END_DATE>
      <BOOKED_ROOM_CATEGORY_LABEL>JDT</BOOKED_ROOM_CATEGORY_LABEL>
      <IS_SHARED_YN>N</IS_SHARED_YN>
      <NAME_ID>5605963</NAME_ID>
      <RESORT3>22974</RESORT3>
      <ROOM_STATUS>DI</ROOM_STATUS>
      <TRAVEL_AGENT_ID></TRAVEL_AGENT_ID>
      <SOURCE_ID></SOURCE_ID>
      <RESV_NAME_ID>24305900</RESV_NAME_ID>
      <RM_ADULTS>2</RM_ADULTS>
      <RM_CHILDREN>0</RM_CHILDREN>
      <FULL_NAME>Gimenez Salas,Rafael Rene,Mr.</FULL_NAME>
      <FULL_NAME_NO_SHR_IND>Gimenez Salas,Rafael Rene,Mr.</FULL_NAME_NO_SHR_IND>
      <COMPANY_NAME>C- Concorde Margarita</COMPANY_NAME>
      <GROUP_NAME>Time Share</GROUP_NAME>
      <MARKET_CODE>CNT</MARKET_CODE>
      <VIP></VIP>
      <RATE_CODE>CNT01B</RATE_CODE>
      <ROOM_CATEGORY_LABEL>JDT</ROOM_CATEGORY_LABEL>
      <ROOM>1805</ROOM>
      <NIGHTS>5</NIGHTS>
      <DISCOUNT_REASON_CODE></DISCOUNT_REASON_CODE>
      <BLOCK_CODE></BLOCK_CODE>
      <ORIGIN_OF_BOOKING>TIME</ORIGIN_OF_BOOKING>
      <ROOM_NO>                1805</ROOM_NO>
      <CH></CH>
      <PAYMENT_METHOD>CA</PAYMENT_METHOD>
      <CREDIT_CARD_NO></CREDIT_CARD_NO>
      <CREDIT_CARD_EXP_DATE></CREDIT_CARD_EXP_DATE>
      <SOURCE_COMM>N</SOURCE_COMM>
      <PRODUCTS></PRODUCTS>
      <RM_DISC_AMT></RM_DISC_AMT>
      <RM_DIS_PERCENT></RM_DIS_PERCENT>
      <RM_GROSS_RATE>0</RM_GROSS_RATE>
      <RM_NET_ROOM_REVENUE>0</RM_NET_ROOM_REVENUE>
      <RM_POT_GROSS_RATE>0</RM_POT_GROSS_RATE>
      <RM_POT_NET_ROOM_REVENUE>0</RM_POT_NET_ROOM_REVENUE>
      <DISCOUNT_REASON_DESC></DISCOUNT_REASON_DESC>
      <PRIMARY_01>1</PRIMARY_01>
      <CHANNEL>MAIL</CHANNEL>
      <LIST_G_RESERVATION_NOTES>
      </LIST_G_RESERVATION_NOTES>
      <LIST_G_PROFILE_NOTES>
      </LIST_G_PROFILE_NOTES>
      <LIST_G_ROUTING_INSTRUCTIONS>
      </LIST_G_ROUTING_INSTRUCTIONS>
      <COMM_YN>N</COMM_YN>
      <RM_NET_VARIANCE>0</RM_NET_VARIANCE>
      <COUNT_COMMENTS>0</COUNT_COMMENTS>
      <COUNT_RES_COMMENTS>0</COUNT_RES_COMMENTS>
      <COUNT_ROUTING>0</COUNT_ROUTING>
    </G_ROOM>
    <G_ROOM>
      <IS_ACCOMPANYING_YN>N</IS_ACCOMPANYING_YN>
      <SHARE_NAMES></SHARE_NAMES>
      <ACCOMPANYING_NAMES></ACCOMPANYING_NAMES>
      <BOOKED_ROOM_CATEGORY>10822</BOOKED_ROOM_CATEGORY>
      <RECORD_TYPE>RESERVATION</RECORD_TYPE>
      <COMMISIONABLE_YN>N</COMMISIONABLE_YN>
      <ALLOTMENT_HEADER_ID></ALLOTMENT_HEADER_ID>
      <CHAR_ARRIVAL>15-04-22</CHAR_ARRIVAL>
      <CHAR_DEPARTURE>01-06-22</CHAR_DEPARTURE>
      <BEGIN_DATE>15-APR-22</BEGIN_DATE>
      <END_DATE>01-JUN-22</END_DATE>
      <BOOKED_ROOM_CATEGORY_LABEL>FST</BOOKED_ROOM_CATEGORY_LABEL>
      <IS_SHARED_YN>N</IS_SHARED_YN>
      <NAME_ID>617963</NAME_ID>
      <RESORT3>22974</RESORT3>
      <ROOM_STATUS>DI</ROOM_STATUS>
      <TRAVEL_AGENT_ID></TRAVEL_AGENT_ID>
      <SOURCE_ID></SOURCE_ID>
      <RESV_NAME_ID>24216150</RESV_NAME_ID>
      <RM_ADULTS>1</RM_ADULTS>
      <RM_CHILDREN>0</RM_CHILDREN>
      <FULL_NAME>Showroom,Showroom</FULL_NAME>
      <FULL_NAME_NO_SHR_IND>Showroom,Showroom</FULL_NAME_NO_SHR_IND>
      <COMPANY_NAME>C- Concorde Margarita</COMPANY_NAME>
      <GROUP_NAME>TimeShare3</GROUP_NAME>
      <MARKET_CODE>CNT</MARKET_CODE>
      <VIP></VIP>
      <RATE_CODE>CNT01B</RATE_CODE>
      <ROOM_CATEGORY_LABEL>FST</ROOM_CATEGORY_LABEL>
      <ROOM>1806</ROOM>
      <NIGHTS>47</NIGHTS>
      <DISCOUNT_REASON_CODE></DISCOUNT_REASON_CODE>
      <BLOCK_CODE></BLOCK_CODE>
      <ORIGIN_OF_BOOKING>TIME</ORIGIN_OF_BOOKING>
      <ROOM_NO>                1806</ROOM_NO>
      <CH></CH>
      <PAYMENT_METHOD>CA</PAYMENT_METHOD>
      <CREDIT_CARD_NO></CREDIT_CARD_NO>
      <CREDIT_CARD_EXP_DATE></CREDIT_CARD_EXP_DATE>
      <SOURCE_COMM>N</SOURCE_COMM>
      <PRODUCTS></PRODUCTS>
      <RM_DISC_AMT></RM_DISC_AMT>
      <RM_DIS_PERCENT></RM_DIS_PERCENT>
      <RM_GROSS_RATE>0</RM_GROSS_RATE>
      <RM_NET_ROOM_REVENUE>0</RM_NET_ROOM_REVENUE>
      <RM_POT_GROSS_RATE>0</RM_POT_GROSS_RATE>
      <RM_POT_NET_ROOM_REVENUE>0</RM_POT_NET_ROOM_REVENUE>
      <DISCOUNT_REASON_DESC></DISCOUNT_REASON_DESC>
      <PRIMARY_01>1</PRIMARY_01>
      <CHANNEL>MAIL</CHANNEL>
      <LIST_G_RESERVATION_NOTES>
      </LIST_G_RESERVATION_NOTES>
      <LIST_G_PROFILE_NOTES>
      </LIST_G_PROFILE_NOTES>
      <LIST_G_ROUTING_INSTRUCTIONS>
      </LIST_G_ROUTING_INSTRUCTIONS>
      <COMM_YN>N</COMM_YN>
      <RM_NET_VARIANCE>0</RM_NET_VARIANCE>
      <COUNT_COMMENTS>0</COUNT_COMMENTS>
      <COUNT_RES_COMMENTS>0</COUNT_RES_COMMENTS>
      <COUNT_ROUTING>0</COUNT_ROUTING>
    </G_ROOM>
  </LIST_G_ROOM>
  <LIST_G_TOTAL>
  </LIST_G_TOTAL>
  <LIST_G_MASTER_MCODE>
  </LIST_G_MASTER_MCODE>
  <LIST_G_ROOM_CATEGORY>
  </LIST_G_ROOM_CATEGORY>
  <REP_GROSS_RATE>13270.93</REP_GROSS_RATE>
  <REP_DISC_AMOUNT></REP_DISC_AMOUNT>
  <REP_NET_ROOM_REVENUE>11820.84</REP_NET_ROOM_REVENUE>
  <REP_POT_NET_ROOM_REVENUE>0</REP_POT_NET_ROOM_REVENUE>
  <REP_NET_VARIANCE>-11820.84</REP_NET_VARIANCE>
  <LOGO></LOGO>
  <TOTAL_MKT_POT_NET>0</TOTAL_MKT_POT_NET>
  <TOT_MKT_ROOMS></TOT_MKT_ROOMS>
  <TOT_MKT_ROOMS_AT_RA></TOT_MKT_ROOMS_AT_RA>
  <TOT_MKT_POT_GROSS_REV></TOT_MKT_POT_GROSS_REV>
  <TOT_MKT_ACT_GROSS_REV></TOT_MKT_ACT_GROSS_REV>
  <TOT_MKT_ACT_NET_REV>0</TOT_MKT_ACT_NET_REV>
  <TOT_MKT_GROSS_VAR></TOT_MKT_GROSS_VAR>
  <TOT_MKT_NET_VAR>0</TOT_MKT_NET_VAR>
  <TOT_RT_ROOMS></TOT_RT_ROOMS>
  <TOT_RT_ROOMS_AT_RA></TOT_RT_ROOMS_AT_RA>
  <TOT_RT_POT_GROSS_REV></TOT_RT_POT_GROSS_REV>
  <TOT_RT_ACT_GROSS_REV></TOT_RT_ACT_GROSS_REV>
  <TOT_RT_GROSS_VAR></TOT_RT_GROSS_VAR>
  <TOT_RT_POT_NET_REV></TOT_RT_POT_NET_REV>
  <TOT_RT_ACT_NET_REV></TOT_RT_ACT_NET_REV>
  <TOT_RT_NET_VAR></TOT_RT_NET_VAR>
  <TOT_MKT_AVE_RATE_GROSS_REV>0</TOT_MKT_AVE_RATE_GROSS_REV>
  <TOT_MKT_AVE_RATE_NET_REV>0</TOT_MKT_AVE_RATE_NET_REV>
  <TOT_RT_AVE_RATE_GROSS_REV>0</TOT_RT_AVE_RATE_GROSS_REV>
  <TOT_RT_AVE_RATE_NET_REV>0</TOT_RT_AVE_RATE_NET_REV>
</GIRATEVARIANCE>
